Workbook
Name ABONUS_s.r.o.: 'databáza KONTAKTY'!$A$12:$A$169
Name producst: 'databáza KONTAKTY'!$B$1:$B$1
Name products: 'databáza KONTAKTY'!$B$1:$B$1

Sheet Výpis materiálu
D2: =D12 -> ZL-112-24-248 | F2: E.D.T. spol. s r.o., Galvaniho 4324/8, 821 04 Bratislava, Slovensko, IČO: 35 731 761, DIČ: 2020 251 343, IČ DPH: SK 2020 251 343
F3: Tel.: +421 2 43 42 29 51, e-mail: edt@edt.sk, www.edt.sk
F4: Bankové spojenie: Slovenská sporiteľňa, a.s., IBAN: SK97 0900 0000 0051 6609 4679
F5: Registrácia: OR Mestského súdu Bratislava III, oddiel Sro, vložka č.: 15919/B
F7: e-mail | I7: tel. číslo
C8: Zákazník: | D8: =CP!D19 -> 0
C9: V zastúpení: | D9: =CP!D20 -> 0 | F9: =CP!G20 -> 0 | I9: =CP!E20 -> 0
C10: Adresa: | D10: =CP!D21 -> 0
C11: Názov akcie: | D11: =CP!D22 -> Dodávka a montáž klimatizácie
C12: Číslo zákazky: | D12: =CP!D23 -> ZL-112-24-248
C13: Číslo ponuky: | D13: =CP!D24 -> CP-112-24-844
C14: Vybavuje: | D14: =CP!D26 -> Mgr. Martin Holík | F14: =CP!G26 -> 0 | I14: =CP!E26 -> 421902383121
C15: Dátum: | D15: =CP!D29 -> 45714
D16: Zoznam položiek
C18: Kód položky | D18: Popis položky | I18: Množstvo | J18: Merná jednotka
D22: =CP!#REF! -> #REF! | I22: =CP!#REF! -> #REF! | J22: =CP!#REF! -> #REF!
A23: 3 | B23: 3 | D23: =CP!#REF! -> #REF! | I23: =CP!#REF! -> #REF! | J23: =CP!#REF! -> #REF!
D24: =CP!#REF! -> #REF! | I24: =CP!#REF! -> #REF! | J24: =CP!#REF! -> #REF!
D25: =CP!#REF! -> #REF! | I25: =CP!#REF! -> #REF! | J25: =CP!#REF! -> #REF!
D26: =CP!#REF! -> #REF! | I26: =CP!#REF! -> #REF! | J26: =CP!#REF! -> #REF!
D27: =CP!#REF! -> #REF! | I27: =CP!#REF! -> #REF! | J27: =CP!#REF! -> #REF!
D28: =CP!#REF! -> #REF! | I28: =CP!#REF! -> #REF! | J28: =CP!#REF! -> #REF!
D29: =CP!#REF! -> #REF! | I29: =CP!#REF! -> #REF! | J29: =CP!#REF! -> #REF!
D30: =CP!#REF! -> #REF! | I30: =CP!#REF! -> #REF! | J30: =CP!#REF! -> #REF!
D31: =CP!#REF! -> #REF! | I31: =CP!#REF! -> #REF! | J31: =CP!#REF! -> #REF!
D32: =CP!#REF! -> #REF! | I32: =CP!#REF! -> #REF! | J32: =CP!#REF! -> #REF!
D33: =CP!#REF! -> #REF! | I33: =CP!#REF! -> #REF! | J33: =CP!#REF! -> #REF!
D34: =CP!#REF! -> #REF! | I34: =CP!#REF! -> #REF! | J34: =CP!#REF! -> #REF!
D35: =CP!#REF! -> #REF! | I35: =CP!#REF! -> #REF! | J35: =CP!#REF! -> #REF!
D36: =CP!D36 -> 0 | I36: =CP!F36 -> 1 | J36: =CP!E36 -> kpl
D37: =CP!D37 -> 0 | I37: =CP!F37 -> 1 | J37: =CP!E37 -> kpl
D38: =CP!D38 -> 0 | I38: =CP!F38 -> 1 | J38: =CP!E38 -> kpl
D39: =CP!D39 -> 0 | I39: =CP!F39 -> 1 | J39: =CP!E39 -> kpl
D40: =CP!D40 -> 0 | I40: =CP!F40 -> 1 | J40: =CP!E40 -> kpl
D41: =CP!D41 -> 0 | I41: =CP!F41 -> 1 | J41: =CP!E41 -> kpl
D42: =CP!D42 -> 0 | I42: =CP!F42 -> 1 | J42: =CP!E42 -> kpl
D43: =CP!D43 -> 0 | I43: =CP!F43 -> 1 | J43: =CP!E43 -> kpl
D44: =CP!D44 -> 0 | I44: =CP!F44 -> 1 | J44: =CP!E44 -> kpl
D45: =CP!D45 -> 0 | I45: =CP!F45 -> 1 | J45: =CP!E45 -> kpl
D46: =CP!D46 -> 0 | I46: =CP!F46 -> 1 | J46: =CP!E46 -> kpl
D47: =CP!D47 -> 0 | I47: =CP!F47 -> 1 | J47: =CP!E47 -> kpl
... D71: =CP!D71 -> 0 | I71: =CP!F71 -> 1 | J71: =CP!E71 -> kpl
D72: =CP!#REF! -> #REF! | I72: =CP!#REF! -> #REF! | J72: =CP!#REF! -> #REF!
D73: =CP!D72 -> 0 | I73: =CP!F72 -> 0 | J73: =CP!E72 -> 0
D74: =CP!#REF! -> #REF! | I74: =CP!#REF! -> #REF! | J74: =CP!#REF! -> #REF!
D75: =CP!#REF! -> #REF! | I75: =CP!#REF! -> #REF! | J75: =CP!#REF! -> #REF!
D76: =CP!D78 -> 0 | I76: =CP!F78 -> 0 | J76: =CP!E78 -> 0
D77: =CP!D79 -> 0 | I77: =CP!F79 -> 0 | J77: =CP!E79 -> 0
D78: =CP!#REF! -> #REF! | I78: =CP!#REF! -> #REF! | J78: =CP!#REF! -> #REF!
D79: =CP!#REF! -> #REF! | I79: =CP!#REF! -> #REF! | J79: =CP!#REF! -> #REF!
D80: =CP!#REF! -> #REF! | I80: =CP!#REF! -> #REF! | J80: =CP!#REF! -> #REF!
D81: =CP!#REF! -> #REF! | I81: =CP!#REF! -> #REF! | J81: =CP!#REF! -> #REF!
D82: =CP!#REF! -> #REF! | I82: =CP!#REF! -> #REF! | J82: =CP!#REF! -> #REF!
D83: =CP!#REF! -> #REF! | I83: =CP!#REF! -> #REF! | J83: =CP!#REF! -> #REF!
D84: =CP!#REF! -> #REF! | I84: =CP!#REF! -> #REF! | J84: =CP!#REF! -> #REF!
D85: =CP!#REF! -> #REF! | I85: =CP!#REF! -> #REF! | J85: =CP!#REF! -> #REF!
D86: =CP!#REF! -> #REF! | I86: =CP!#REF! -> #REF! | J86: =CP!#REF! -> #REF!
D87: =CP!#REF! -> #REF! | I87: =CP!#REF! -> #REF! | J87: =CP!#REF! -> #REF!
C89: Popis | D89: =CP!D92 -> do 7 dní od potvrdenia objdnávky.

Sheet PP
B1: PREBERACÍ PROTOKOL | D1: označenie | E1: Q-F-3.13
D2: verzia | E2: 2
D3: platnosť od | E3: 29.02.2023
A5: Odovzdávajúci subjekt:
A7: Firma | C7: G.T LABS s.r.o
A8: ZASTÚPENIE / KONTAKT | C8: Mgr. Martin Holík | D8: =VLOOKUP(C8,'databáza KONTAKTY'!$B$1:$F$14,2,FALSE) -> 421902383121 | E8: =VLOOKUP(C8,'databáza KONTAKTY'!$B$1:$F$14,3,FALSE) -> holik@klimafresh.sk
A9: ADRESA | C9: Za mlynom 2, 83107 Bratislava - Vajnory
A10: IČO | C10: 53100972
A11: DIČ | C11: 2121276179
A12: Evidenčné číslo zákazky odovzdávajúceho subjektu | C12: =CP!D23 -> ZL-112-24-248
A14: Preberajúci subjekt: | C14: Spoločnosť Čínska reštaurácia, s.r.o.
A16: Firma | C16: Spoločnosť Čínska reštaurácia, s.r.o.
A17: ZASTÚPENIE / KONTAKT | C17: =CP!D20 -> 0 | D17: =CP!E20 -> 0 | E17: =CP!G20 -> 0
A18: ADRESA | C18: =CP!D21 -> 0
A19: IČO
A20: DIČ
A21: Evidenčné číslo preberacieho subjektu
A23: Hore uvedená firma týmto preberá nasledovný tovar / služby: | C23: 5x DJ35_G_COMFORT_3,5W_IDU | D23: 5x DJ35_W_COMFORT_3,5kW_ODU
A25: Číslo | B25: Tovar / služba | E25: Množstvo
A28: 1 | B28: =CP!D22 -> Dodávka a montáž klimatizácie | E28: 5ks
A32: Týmto hore uvedená firma prehlasuje, že prevzatý tovar/služby bol dodaný nepoškodený v plnom rozsahu v súlade s vystavenou objednávkou.
A34: Prevzatá hotovosť:
A46: =C8 -> Mgr. Martin Holík
A48: Čitateľné meno, pečiatka a podpis | D48: Čitateľné meno, pečiatka a podpis
A49: zástupcu odovzdávajúcej strany | D49: zástupcu preberajúcej strany
A51: V Bratislave, dňa:

Sheet CP
A1: 3 | B1: 1 | D1: hlavný nadpis
A2: 3 | B2: 2 | D2: podnadpis 1
A3: 3 | B3: 3 | D3: podnadpis 2 | E3: kpl | F3: 1000
D4: Hisense Easy CA25 Qch=2,6 kW vnútorná nástenná + vonkajšia | E4: =VLOOKUP(D4,cenniktoshiba!$B$3:$D121,3,FALSE) -> #N/A | F4: 1000 | G4: =H4/F4 -> #N/A | H4: =AK4 -> #N/A | I4: =AK4 -> #N/A | K4: =VLOOKUP(D4,cenniktoshiba!$B$3:$F121,5,FALSE) -> #N/A | L4: =VLOOKUP(D4,cenniktoshiba!$B$3:$C121,2,FALSE) -> #N/A | M4: =VLOOKUP(D4,cenniktoshiba!$B$3:$E121,4,FALSE) -> #N/A | N4: =L4*(1-M4) -> #N/A | O4: =N4*F4 -> #N/A | P4: 0,30 €/km | R4: {=_xlfn.IFS(P4=$P$28,$Q$28,P4=$P$26,Q4*$Q$26,P4=$P$27,Q4*$Q$27,P4=$P$25,Q4*$Q$25,P4=$P$29,$Q$29)} -> 0 | S4: =O4+R4 -> #N/A | T4: 1 | V4: 0 | X4: =IF(W4=$W$27,$X$27,0)+IF(W4=$W$28,$X$28,0)+IF(W4=$W$29,$X$29,0) -> 0 | Y4: =X4*U4*V4*T4 -> 0 | Z4: =Y4*F4 -> 0 | AA4: =S4+Z4 -> #N/A | AB4: =$AB$34 -> 0.3 | AC4: =$AC$34 -> 0.01 | AD4: =S4*AB4 -> #N/A | AE4: =Z4*AC4 -> 0 | AF4: =AD4+AE4 -> #N/A | AG4: =AA4+AF4 -> #N/A | AH4: =$AH$34/$Z$86*AA4 -> #N/A | AI4: =AG4+AH4 -> #N/A | AJ4: =$AJ$34/$AF$86*AF4 -> #N/A | AK4: =AI4+AJ4 -> #N/A | AM4: Powering | AN4: =IF(AM4="Powering",O4) -> #N/A | AO4: =$AO$34 -> 0.01 | AP4: =AN4*AO4 -> #N/A | AQ4: =AN4-AP4 -> #N/A
D5: MATERIÁL BEIJER ANMIMA | E5: =VLOOKUP(D5,'Cenník Beijer Anmima'!$B$3:$D$52,3,FALSE) -> #N/A | F5: 1000 | G5: =H5/F5 -> #N/A | H5: =AK5 -> #N/A | I5: =AK5 -> #N/A | K5: =VLOOKUP(D5,'Cenník Beijer Anmima'!$B$3:$G100,6,FALSE) -> #N/A | L5: =VLOOKUP(D5,'Cenník Beijer Anmima'!$B$2:$C$100,2,FALSE) -> #N/A | M5: 0 | N5: =L5*(1-M5) -> #N/A | O5: =N5*F5 -> #N/A | P5: 0,30 €/km | R5: {=_xlfn.IFS(P5=$P$28,$Q$28,P5=$P$26,Q5*$Q$26,P5=$P$27,Q5*$Q$27,P5=$P$25,Q5*$Q$25,P5=$P$29,$Q$29)} -> 0 | S5: =O5+R5 -> #N/A | T5: 1 | V5: 0 | X5: =IF(W5=$W$27,$X$27,0)+IF(W5=$W$28,$X$28,0)+IF(W5=$W$29,$X$29,0) -> 0 | Y5: =X5*U5*V5*T5 -> 0 | Z5: =Y5*F5 -> 0 | AA5: =S5+Z5 -> #N/A | AB5: =$AB$34 -> 0.3 | AC5: =$AC$34 -> 0.01 | AD5: =S5*AB5 -> #N/A | AE5: =Z5*AC5 -> 0 | AF5: =AD5+AE5 -> #N/A | AG5: =AA5+AF5 -> #N/A | AH5: =$AH$34/$Z$86*AA5 -> #N/A | AI5: =AG5+AH5 -> #N/A | AJ5: =$AJ$34/$AF$86*AF5 -> #N/A | AK5: =AI5+AJ5 -> #N/A | AN5: =IF(AM5="Powering",O5) -> FALSE | AO5: =$AO$34 -> 0.01 | AP5: =AN5*AO5 -> 0 | AQ5: =AN5-AP5 -> 0
D6: Konzola 450 mm s vodováhou (100 kg) | E6: =VLOOKUP(D6,'Cenník Sinclair '!$B$2:$D$43,3,FALSE) -> #N/A | F6: 1000 | G6: =H6/F6 -> #N/A | H6: =AK6 -> #N/A | I6: =AK6 -> #N/A | K6: =VLOOKUP(D6,'Cenník Sinclair '!$B$2:$F$101,5,FALSE) -> #N/A | L6: =VLOOKUP(D6,'Cenník Sinclair '!$B$2:$C$101,2,FALSE) -> #N/A | M6: =VLOOKUP(D6,'Cenník Sinclair '!$B$2:$E$101,4,FALSE) -> #N/A | N6: =L6*(1-M6) -> #N/A | O6: =N6*F6 -> #N/A | P6: 0,30 €/km | R6: {=_xlfn.IFS(P6=$P$28,$Q$28,P6=$P$26,Q6*$Q$26,P6=$P$27,Q6*$Q$27,P6=$P$25,Q6*$Q$25,P6=$P$29,$Q$29)} -> 0 | S6: =O6+R6 -> #N/A | T6: 1 | V6: 0 | X6: =IF(W6=$W$27,$X$27,0)+IF(W6=$W$28,$X$28,0)+IF(W6=$W$29,$X$29,0) -> 0 | Y6: =X6*U6*V6*T6 -> 0 | Z6: =Y6*F6 -> 0 | AA6: =S6+Z6 -> #N/A | AB6: =$AB$34 -> 0.3 | AC6: =$AC$34 -> 0.01 | AD6: =S6*AB6 -> #N/A | AE6: =Z6*AC6 -> 0 | AF6: =AD6+AE6 -> #N/A | AG6: =AA6+AF6 -> #N/A | AH6: =$AH$34/$Z$86*AA6 -> #N/A | AI6: =AG6+AH6 -> #N/A | AJ6: =$AJ$34/$AF$86*AF6 -> #N/A | AK6: =AI6+AJ6 -> #N/A | AN6: =IF(AM6="Powering",O6) -> FALSE | AO6: =$AO$34 -> 0.01 | AP6: =AN6*AO6 -> 0 | AQ6: =AN6-AP6 -> 0
D7: VIVAX | E7: =VLOOKUP(D7,'Cenník Sinclair '!$B$2:$D$43,3,FALSE) -> #N/A | F7: 1001 | G7: =H7/F7 -> #N/A | H7: =AK7 -> #N/A | I7: =AK7 -> #N/A | K7: =VLOOKUP(D7,'Cenník Sinclair '!$B$2:$F$101,5,FALSE) -> #N/A | L7: =VLOOKUP(D7,'Cenník Sinclair '!$B$2:$C$101,2,FALSE) -> #N/A | M7: =VLOOKUP(D7,'Cenník Sinclair '!$B$2:$E$101,4,FALSE) -> #N/A | N7: =L7*(1-M7) -> #N/A | O7: =N7*F7 -> #N/A | P7: 0,30 €/km | R7: {=_xlfn.IFS(P7=$P$28,$Q$28,P7=$P$26,Q7*$Q$26,P7=$P$27,Q7*$Q$27,P7=$P$25,Q7*$Q$25,P7=$P$29,$Q$29)} -> 0 | S7: =O7+R7 -> #N/A | T7: 1 | V7: 0 | X7: =IF(W7=$W$27,$X$27,0)+IF(W7=$W$28,$X$28,0)+IF(W7=$W$29,$X$29,0) -> 0 | Y7: =X7*U7*V7*T7 -> 0 | Z7: =Y7*F7 -> 0 | AA7: =S7+Z7 -> #N/A | AB7: =$AB$34 -> 0.3 | AC7: =$AC$34 -> 0.01 | AD7: =S7*AB7 -> #N/A | AE7: =Z7*AC7 -> 0 | AF7: =AD7+AE7 -> #N/A | AG7: =AA7+AF7 -> #N/A | AH7: =$AH$34/$Z$86*AA7 -> #N/A | AI7: =AG7+AH7 -> #N/A | AJ7: =$AJ$34/$AF$86*AF7 -> #N/A | AK7: =AI7+AJ7 -> #N/A | AN7: =IF(AM7="Powering",O7) -> FALSE | AO7: =$AO$34 -> 0.01 | AP7: =AN7*AO7 -> 0 | AQ7: =AN7-AP7 -> 0
D8: SINCLAIR | E8: =VLOOKUP(D8,'Cenník Sinclair '!$B$2:$D$43,3,FALSE) -> #N/A | F8: 1001 | G8: =H8/F8 -> #N/A | H8: =AK8 -> #N/A | I8: =AK8 -> #N/A | K8: =VLOOKUP(D8,'Cenník Sinclair '!$B$2:$F$101,5,FALSE) -> #N/A | L8: =VLOOKUP(D8,'Cenník Sinclair '!$B$2:$C$101,2,FALSE) -> #N/A | M8: =VLOOKUP(D8,'Cenník Sinclair '!$B$2:$E$101,4,FALSE) -> #N/A | N8: =L8*(1-M8) -> #N/A | O8: =N8*F8 -> #N/A | P8: 0,30 €/km | R8: {=_xlfn.IFS(P8=$P$28,$Q$28,P8=$P$26,Q8*$Q$26,P8=$P$27,Q8*$Q$27,P8=$P$25,Q8*$Q$25,P8=$P$29,$Q$29)} -> 0 | S8: =O8+R8 -> #N/A | T8: 1 | V8: 0 | X8: =IF(W8=$W$27,$X$27,0)+IF(W8=$W$28,$X$28,0)+IF(W8=$W$29,$X$29,0) -> 0 | Y8: =X8*U8*V8*T8 -> 0 | Z8: =Y8*F8 -> 0 | AA8: =S8+Z8 -> #N/A | AB8: =$AB$34 -> 0.3 | AC8: =$AC$34 -> 0.01 | AD8: =S8*AB8 -> #N/A | AE8: =Z8*AC8 -> 0 | AF8: =AD8+AE8 -> #N/A | AG8: =AA8+AF8 -> #N/A | AH8: =$AH$34/$Z$86*AA8 -> #N/A | AI8: =AG8+AH8 -> #N/A | AJ8: =$AJ$34/$AF$86*AF8 -> #N/A | AK8: =AI8+AJ8 -> #N/A | AN8: =IF(AM8="Powering",O8) -> FALSE | AO8: =$AO$34 -> 0.01 | AP8: =AN8*AO8 -> 0 | AQ8: =AN8-AP8 -> 0
A9: c | D9: MITSUBISHI | E9: =VLOOKUP(D9,'Cenník Mitsubishi'!$B$2:$D$116,3,FALSE) -> #N/A | F9: 1 | G9: =H9/F9 -> #N/A | H9: =AK9 -> #N/A | I9: =AK9 -> #N/A | K9: =VLOOKUP(D9,'Cenník Mitsubishi'!$B$2:$F$116,5,FALSE) -> #N/A | L9: =VLOOKUP(D9,'Cenník Mitsubishi'!$B$2:$F$116,2,FALSE) -> #N/A | M9: =VLOOKUP(D9,'Cenník Mitsubishi'!$B$2:$F$120,4,FALSE) -> #N/A | N9: =L9*(1-M9) -> #N/A | O9: =N9*F9 -> #N/A | P9: 0,30 €/km | R9: {=_xlfn.IFS(P9=$P$28,$Q$28,P9=$P$26,Q9*$Q$26,P9=$P$27,Q9*$Q$27,P9=$P$25,Q9*$Q$25,P9=$P$29,$Q$29)} -> 0 | S9: =O9+R9 -> #N/A | T9: 1 | V9: 0 | X9: =IF(W9=$W$27,$X$27,0)+IF(W9=$W$28,$X$28,0)+IF(W9=$W$29,$X$29,0) -> 0 | Y9: =X9*U9*V9*T9 -> 0 | Z9: =Y9*F9 -> 0 | AA9: =S9+Z9 -> #N/A | AB9: =$AB$34 -> 0.3 | AC9: =$AC$34 -> 0.01 | AD9: =S9*AB9 -> #N/A | AE9: =Z9*AC9 -> 0 | AF9: =AD9+AE9 -> #N/A | AG9: =AA9+AF9 -> #N/A | AH9: =$AH$34/$Z$86*AA9 -> #N/A | AI9: =AG9+AH9 -> #N/A | AJ9: =$AJ$34/$AF$86*AF9 -> #N/A | AK9: =AI9+AJ9 -> #N/A | AN9: =IF(AM9="Powering",O9) -> FALSE | AO9: =$AO$34 -> 0.01 | AP9: =AN9*AO9 -> 0 | AQ9: =AN9-AP9 -> 0
D10: TOSHIBA | E10: =VLOOKUP(D10,#REF!,3,FALSE) -> #REF! | F10: 1000 | G10: =H10/F10 -> #REF! | H10: =AK10 -> #REF! | I10: =AK10 -> #REF! | K10: =VLOOKUP(D10,#REF!,5,FALSE) -> #REF! | L10: =VLOOKUP(D10,#REF!,2,FALSE) -> #REF! | M10: =VLOOKUP(D10,#REF!,4,FALSE) -> #REF! | N10: =L10*(1-M10) -> #REF! | O10: =N10*F10 -> #REF! | P10: 0,30 €/km | R10: {=_xlfn.IFS(P10=$P$28,$Q$28,P10=$P$26,Q10*$Q$26,P10=$P$27,Q10*$Q$27,P10=$P$25,Q10*$Q$25,P10=$P$29,$Q$29)} -> 0 | S10: =O10+R10 -> #REF! | T10: 1 | V10: 0 | X10: =IF(W10=$W$27,$X$27,0)+IF(W10=$W$28,$X$28,0)+IF(W10=$W$29,$X$29,0) -> 0 | Y10: =X10*U10*V10*T10 -> 0 | Z10: =Y10*F10 -> 0 | AA10: =S10+Z10 -> #REF! | AB10: =$AB$34 -> 0.3 | AC10: =$AC$34 -> 0.01 | AD10: =S10*AB10 -> #REF! | AE10: =Z10*AC10 -> 0 | AF10: =AD10+AE10 -> #REF! | AG10: =AA10+AF10 -> #REF! | AH10: =$AH$34/$Z$86*AA10 -> #N/A | AI10: =AG10+AH10 -> #REF! | AJ10: =$AJ$34/$AF$86*AF10 -> #N/A | AK10: =AI10+AJ10 -> #REF! | AN10: =IF(AM10="Powering",O10) -> FALSE | AO10: =$AO$34 -> 0.01 | AP10: =AN10*AO10 -> 0 | AQ10: =AN10-AP10 -> 0
D11: PANASONIC | E11: =VLOOKUP(D11,#REF!,3,FALSE) -> #REF! | F11: 1000 | G11: =H11/F11 -> #REF! | H11: =AK11 -> #REF! | I11: =AK11 -> #REF! | K11: =VLOOKUP(D11,#REF!,5,FALSE) -> #REF! | L11: =VLOOKUP(D11,#REF!,2,FALSE) -> #REF! | M11: =VLOOKUP(D11,#REF!,4,FALSE) -> #REF! | N11: =L11*(1-M11) -> #REF! | O11: =N11*F11 -> #REF! | P11: 0,30 €/km | R11: {=_xlfn.IFS(P11=$P$28,$Q$28,P11=$P$26,Q11*$Q$26,P11=$P$27,Q11*$Q$27,P11=$P$25,Q11*$Q$25,P11=$P$29,$Q$29)} -> 0 | S11: =O11+R11 -> #REF! | T11: 1 | V11: 0 | X11: =IF(W11=$W$27,$X$27,0)+IF(W11=$W$28,$X$28,0)+IF(W11=$W$29,$X$29,0) -> 0 | Y11: =X11*U11*V11*T11 -> 0 | Z11: =Y11*F11 -> 0 | AA11: =S11+Z11 -> #REF! | AB11: =$AB$34 -> 0.3 | AC11: =$AC$34 -> 0.01 | AD11: =S11*AB11 -> #REF! | AE11: =Z11*AC11 -> 0 | AF11: =AD11+AE11 -> #REF! | AG11: =AA11+AF11 -> #REF! | AH11: =$AH$34/$Z$86*AA11 -> #N/A | AI11: =AG11+AH11 -> #REF! | AJ11: =$AJ$34/$AF$86*AF11 -> #N/A | AK11: =AI11+AJ11 -> #REF! | AN11: =IF(AM11="Powering",O11) -> FALSE | AO11: =$AO$34 -> 0.01 | AP11: =AN11*AO11 -> 0 | AQ11: =AN11-AP11 -> 0
C17: CP-112-24-844 | E17: GT Labs s.r.o. IČO 53100972 DIČ 2121276179IČ DPHSK2121276179, podľa §4, registrácia od 5.11.2022 Sídlo GT LABS, s.r.o. Za mlynom 2 831 07 Bratislava - mestská časť Vajnory
E18: tel. číslo | G18: e-mail
C19: Zákazník: | E19: 421910950582 | I19: mgr.peterlani@gmail.com
C20: V zastúpení:
C21: Adresa:
C22: Názov akcie: | D22: Dodávka a montáž klimatizácie
C23: Číslo zákazky: | D23: ZL-112-24-248
C24: Číslo ponuky: | D24: CP-112-24-844 | L24: ZĽAVA | P24: DOPRAVA | Q24: €/km
C25: Revízia: | D25: R1 | L25: Hisense | M25: 0.52 | P25: 0,30 €/km | Q25: 0.3 | W25: MONTÁŽNICI
C26: Vybavuje: | D26: Mgr. Martin Holík | E26: =VLOOKUP(D26,'databáza KONTAKTY'!$B$1:$F$10,2,FALSE) -> 421902383121 | L26: Powering | M26: 0.5 | P26: 0,50 €/km | Q26: 0.5 | W26: Typ | X26: Eur/hod
C27: Vypracoval: | D27: Mgr. Martin Holík | E27: =VLOOKUP(D27,'databáza KONTAKTY'!$B$1:$F$10,2,FALSE) -> 421902383121 | P27: 0,70 €/km | Q27: 0.7 | W27: Technik | X27: 22
C28: Schválil | D28: Mgr. Martin Holík | E28: =VLOOKUP(D28,'databáza KONTAKTY'!$B$1:$F$10,2,FALSE) -> 421902383121 | L28: PRÍPLATOK | P28: Suma 1 | Q28: 10 | W28: MaR | X28: 35
C29: Dátum: | D29: =TODAY() -> 45714 | L29: Tvarovky | M29: 0.3 | P29: Suma 2 | Q29: 15 | W29: Dozor | X29: 25
D30: Cenotvorba
K31: NÁKLADY | AB31: ZISK | AG31: VÝSLEDNÁ CENA | AM31: ZĽAVA NA PROJEKT - POWERING
C32: Kód položky | D32: Popis položky | E32: Merná jednotka | F32: Množstvo | G32: Jednotková cena | H32: Cena spolu | I32: Cena spolu | K32: DODÁVKA | T32: MONTÁŽ | AA32: NÁKLAD SPOLU | AB32: MARŽA | AD32: ZISK | AG32: ROZPUSTENÉ | AK32: KONEČNÁ CENA
K33: NÁKUP | P33: DOPRAVA | S33: Dodávka spolu | T33: Počet dní | U33: Počet hodín | V33: Počet ľudí | W33: Typ montáž-nika | X33: Hodinovka | Y33: Jedn. cena montáž | Z33: Montáž spolu | AB33: Dodávka | AC33: Montáž | AD33: Dodávka | AE33: Montáž | AF33: ZISK SPOLU | AG33: Rozpustený náklad | AI33: Rozpustený zisk | AM33: Dodávateľ | AN33: Pôvodná nákupná cena | AO33: Zľava | AP33: Suma zľavy | AQ33: Zľavnená nákupná cena
K34: Dodávateľ | L34: Jednotková cena | M34: zľava (%) | N34: Jedn. cena po zľave | O34: Nákup spolu | P34: Typ dopravy | Q34: Počet km spolu | R34: Doprava spolu | AB34: 0.3 | AC34: 0.01 | AG34: Náklad + zisk | AH34: 0 | AI34: Náklad + zisk + rozp. náklad | AJ34: 0 | AO34: 0.01
E36: kpl | F36: 1 | G36: =H36/F36 -> #N/A | H36: =AK36 -> #N/A | I36: 0 | N36: =L36*(1-M36) -> 0 | O36: =N36*F36 -> 0 | P36: 0,30 €/km | R36: {=_xlfn.IFS(P36=$P$28,$Q$28,P36=$P$26,Q36*$Q$26,P36=$P$27,Q36*$Q$27,P36=$P$25,Q36*$Q$25,P36=$P$29,$Q$29)} -> 0 | S36: =O36+R36 -> 0 | T36: 1 | V36: 0 | X36: =IF(W36=$W$27,$X$27,0)+IF(W36=$W$28,$X$28,0)+IF(W36=$W$29,$X$29,0) -> 0 | Y36: =X36*U36*V36*T36 -> 0 | Z36: =Y36*F36 -> 0 | AA36: =S36+Z36 -> 0 | AB36: 0.43 | AC36: =$AC$34 -> 0.01 | AD36: =S36*AB36 -> 0 | AE36: =Z36*AC36 -> 0 | AF36: =AD36+AE36 -> 0 | AG36: =AA36+AF36 -> 0 | AH36: =$AH$34/$Z$86*AA36 -> #N/A | AI36: =AG36+AH36 -> #N/A | AJ36: =$AJ$34/$AF$86*AF36 -> #N/A | AK36: =AI36+AJ36 -> #N/A | AN36: =IF(AM36="Powering",O36) -> FALSE | AO36: =$AO$34 -> 0.01 | AP36: =AN36*AO36 -> 0 | AQ36: =AN36-AP36 -> 0
E37: kpl | F37: 1 | G37: =H37/F37 -> #N/A | H37: =AK37 -> #N/A | I37: 0 | N37: =L37*(1-M37) -> 0 | O37: =N37*F37 -> 0 | P37: 0,30 €/km | R37: {=_xlfn.IFS(P37=$P$28,$Q$28,P37=$P$26,Q37*$Q$26,P37=$P$27,Q37*$Q$27,P37=$P$25,Q37*$Q$25,P37=$P$29,$Q$29)} -> 0 | S37: =O37+R37 -> 0 | T37: 1 | V37: 0 | X37: =IF(W37=$W$27,$X$27,0)+IF(W37=$W$28,$X$28,0)+IF(W37=$W$29,$X$29,0) -> 0 | Y37: =X37*U37*V37*T37 -> 0 | Z37: =Y37*F37 -> 0 | AA37: =S37+Z37 -> 0 | AB37: 0.43 | AC37: =$AC$34 -> 0.01 | AD37: =S37*AB37 -> 0 | AE37: =Z37*AC37 -> 0 | AF37: =AD37+AE37 -> 0 | AG37: =AA37+AF37 -> 0 | AH37: =$AH$34/$Z$86*AA37 -> #N/A | AI37: =AG37+AH37 -> #N/A | AJ37: =$AJ$34/$AF$86*AF37 -> #N/A | AK37: =AI37+AJ37 -> #N/A | AN37: =IF(AM37="Powering",O37) -> FALSE | AO37: =$AO$34 -> 0.01 | AP37: =AN37*AO37 -> 0 | AQ37: =AN37-AP37 -> 0
E38: kpl | F38: 1 | G38: =H38/F38 -> #N/A | H38: =AK38 -> #N/A | I38: 0 | N38: =L38*(1-M38) -> 0 | O38: =N38*F38 -> 0 | P38: 0,30 €/km | R38: {=_xlfn.IFS(P38=$P$28,$Q$28,P38=$P$26,Q38*$Q$26,P38=$P$27,Q38*$Q$27,P38=$P$25,Q38*$Q$25,P38=$P$29,$Q$29)} -> 0 | S38: =O38+R38 -> 0 | T38: 1 | V38: 0 | X38: =IF(W38=$W$27,$X$27,0)+IF(W38=$W$28,$X$28,0)+IF(W38=$W$29,$X$29,0) -> 0 | Y38: =X38*U38*V38*T38 -> 0 | Z38: =Y38*F38 -> 0 | AA38: =S38+Z38 -> 0 | AB38: 0.43 | AC38: =$AC$34 -> 0.01 | AD38: =S38*AB38 -> 0 | AE38: =Z38*AC38 -> 0 | AF38: =AD38+AE38 -> 0 | AG38: =AA38+AF38 -> 0 | AH38: =$AH$34/$Z$86*AA38 -> #N/A | AI38: =AG38+AH38 -> #N/A | AJ38: =$AJ$34/$AF$86*AF38 -> #N/A | AK38: =AI38+AJ38 -> #N/A | AN38: =IF(AM38="Powering",O38) -> FALSE | AO38: =$AO$34 -> 0.01 | AP38: =AN38*AO38 -> 0 | AQ38: =AN38-AP38 -> 0
E39: kpl | F39: 1 | G39: =H39/F39 -> #N/A | H39: =AK39 -> #N/A | I39: 0 | N39: =L39*(1-M39) -> 0 | O39: =N39*F39 -> 0 | P39: 0,30 €/km | R39: {=_xlfn.IFS(P39=$P$28,$Q$28,P39=$P$26,Q39*$Q$26,P39=$P$27,Q39*$Q$27,P39=$P$25,Q39*$Q$25,P39=$P$29,$Q$29)} -> 0 | S39: =O39+R39 -> 0 | T39: 1 | V39: 0 | X39: =IF(W39=$W$27,$X$27,0)+IF(W39=$W$28,$X$28,0)+IF(W39=$W$29,$X$29,0) -> 0 | Y39: =X39*U39*V39*T39 -> 0 | Z39: =Y39*F39 -> 0 | AA39: =S39+Z39 -> 0 | AB39: 0.43 | AC39: =$AC$34 -> 0.01 | AD39: =S39*AB39 -> 0 | AE39: =Z39*AC39 -> 0 | AF39: =AD39+AE39 -> 0 | AG39: =AA39+AF39 -> 0 | AH39: =$AH$34/$Z$86*AA39 -> #N/A | AI39: =AG39+AH39 -> #N/A | AJ39: =$AJ$34/$AF$86*AF39 -> #N/A | AK39: =AI39+AJ39 -> #N/A | AN39: =IF(AM39="Powering",O39) -> FALSE | AO39: =$AO$34 -> 0.01 | AP39: =AN39*AO39 -> 0 | AQ39: =AN39-AP39 -> 0
E40: kpl | F40: 1 | G40: =H40/F40 -> #N/A | H40: =AK40 -> #N/A | I40: 0 | N40: =L40*(1-M40) -> 0 | O40: =N40*F40 -> 0 | P40: 0,30 €/km | R40: {=_xlfn.IFS(P40=$P$28,$Q$28,P40=$P$26,Q40*$Q$26,P40=$P$27,Q40*$Q$27,P40=$P$25,Q40*$Q$25,P40=$P$29,$Q$29)} -> 0 | S40: =O40+R40 -> 0 | T40: 1 | V40: 0 | X40: =IF(W40=$W$27,$X$27,0)+IF(W40=$W$28,$X$28,0)+IF(W40=$W$29,$X$29,0) -> 0 | Y40: =X40*U40*V40*T40 -> 0 | Z40: =Y40*F40 -> 0 | AA40: =S40+Z40 -> 0 | AB40: 0.43 | AC40: =$AC$34 -> 0.01 | AD40: =S40*AB40 -> 0 | AE40: =Z40*AC40 -> 0 | AF40: =AD40+AE40 -> 0 | AG40: =AA40+AF40 -> 0 | AH40: =$AH$34/$Z$86*AA40 -> #N/A | AI40: =AG40+AH40 -> #N/A | AJ40: =$AJ$34/$AF$86*AF40 -> #N/A | AK40: =AI40+AJ40 -> #N/A | AN40: =IF(AM40="Powering",O40) -> FALSE | AO40: =$AO$34 -> 0.01 | AP40: =AN40*AO40 -> 0 | AQ40: =AN40-AP40 -> 0
E41: kpl | F41: 1 | G41: =H41/F41 -> #N/A | H41: =AK41 -> #N/A | I41: 0 | N41: =L41*(1-M41) -> 0 | O41: =N41*F41 -> 0 | P41: 0,30 €/km | R41: {=_xlfn.IFS(P41=$P$28,$Q$28,P41=$P$26,Q41*$Q$26,P41=$P$27,Q41*$Q$27,P41=$P$25,Q41*$Q$25,P41=$P$29,$Q$29)} -> 0 | S41: =O41+R41 -> 0 | T41: 1 | V41: 0 | X41: =IF(W41=$W$27,$X$27,0)+IF(W41=$W$28,$X$28,0)+IF(W41=$W$29,$X$29,0) -> 0 | Y41: =X41*U41*V41*T41 -> 0 | Z41: =Y41*F41 -> 0 | AA41: =S41+Z41 -> 0 | AB41: 0.43 | AC41: =$AC$34 -> 0.01 | AD41: =S41*AB41 -> 0 | AE41: =Z41*AC41 -> 0 | AF41: =AD41+AE41 -> 0 | AG41: =AA41+AF41 -> 0 | AH41: =$AH$34/$Z$86*AA41 -> #N/A | AI41: =AG41+AH41 -> #N/A | AJ41: =$AJ$34/$AF$86*AF41 -> #N/A | AK41: =AI41+AJ41 -> #N/A | AN41: =IF(AM41="Powering",O41) -> FALSE | AO41: =$AO$34 -> 0.01 | AP41: =AN41*AO41 -> 0 | AQ41: =AN41-AP41 -> 0
E42: kpl | F42: 1 | G42: =H42/F42 -> #N/A | H42: =AK42 -> #N/A | I42: 0 | N42: =L42*(1-M42) -> 0 | O42: =N42*F42 -> 0 | P42: 0,30 €/km | R42: {=_xlfn.IFS(P42=$P$28,$Q$28,P42=$P$26,Q42*$Q$26,P42=$P$27,Q42*$Q$27,P42=$P$25,Q42*$Q$25,P42=$P$29,$Q$29)} -> 0 | S42: =O42+R42 -> 0 | T42: 1 | V42: 0 | X42: =IF(W42=$W$27,$X$27,0)+IF(W42=$W$28,$X$28,0)+IF(W42=$W$29,$X$29,0) -> 0 | Y42: =X42*U42*V42*T42 -> 0 | Z42: =Y42*F42 -> 0 | AA42: =S42+Z42 -> 0 | AB42: 0.43 | AC42: =$AC$34 -> 0.01 | AD42: =S42*AB42 -> 0 | AE42: =Z42*AC42 -> 0 | AF42: =AD42+AE42 -> 0 | AG42: =AA42+AF42 -> 0 | AH42: =$AH$34/$Z$86*AA42 -> #N/A | AI42: =AG42+AH42 -> #N/A | AJ42: =$AJ$34/$AF$86*AF42 -> #N/A | AK42: =AI42+AJ42 -> #N/A | AN42: =IF(AM42="Powering",O42) -> FALSE | AO42: =$AO$34 -> 0.01 | AP42: =AN42*AO42 -> 0 | AQ42: =AN42-AP42 -> 0
E43: kpl | F43: 1 | G43: =H43/F43 -> #N/A | H43: =AK43 -> #N/A | I43: 0 | N43: =L43*(1-M43) -> 0 | O43: =N43*F43 -> 0 | P43: 0,30 €/km | R43: {=_xlfn.IFS(P43=$P$28,$Q$28,P43=$P$26,Q43*$Q$26,P43=$P$27,Q43*$Q$27,P43=$P$25,Q43*$Q$25,P43=$P$29,$Q$29)} -> 0 | S43: =O43+R43 -> 0 | T43: 1 | V43: 0 | X43: =IF(W43=$W$27,$X$27,0)+IF(W43=$W$28,$X$28,0)+IF(W43=$W$29,$X$29,0) -> 0 | Y43: =X43*U43*V43*T43 -> 0 | Z43: =Y43*F43 -> 0 | AA43: =S43+Z43 -> 0 | AB43: 0.43 | AC43: =$AC$34 -> 0.01 | AD43: =S43*AB43 -> 0 | AE43: =Z43*AC43 -> 0 | AF43: =AD43+AE43 -> 0 | AG43: =AA43+AF43 -> 0 | AH43: =$AH$34/$Z$86*AA43 -> #N/A | AI43: =AG43+AH43 -> #N/A | AJ43: =$AJ$34/$AF$86*AF43 -> #N/A | AK43: =AI43+AJ43 -> #N/A | AN43: =IF(AM43="Powering",O43) -> FALSE | AO43: =$AO$34 -> 0.01 | AP43: =AN43*AO43 -> 0 | AQ43: =AN43-AP43 -> 0
E44: kpl | F44: 1 | G44: =H44/F44 -> #N/A | H44: =AK44 -> #N/A | I44: 0 | N44: =L44*(1-M44) -> 0 | O44: =N44*F44 -> 0 | P44: 0,30 €/km | R44: {=_xlfn.IFS(P44=$P$28,$Q$28,P44=$P$26,Q44*$Q$26,P44=$P$27,Q44*$Q$27,P44=$P$25,Q44*$Q$25,P44=$P$29,$Q$29)} -> 0 | S44: =O44+R44 -> 0 | T44: 1 | V44: 0 | X44: =IF(W44=$W$27,$X$27,0)+IF(W44=$W$28,$X$28,0)+IF(W44=$W$29,$X$29,0) -> 0 | Y44: =X44*U44*V44*T44 -> 0 | Z44: =Y44*F44 -> 0 | AA44: =S44+Z44 -> 0 | AB44: 0.43 | AC44: =$AC$34 -> 0.01 | AD44: =S44*AB44 -> 0 | AE44: =Z44*AC44 -> 0 | AF44: =AD44+AE44 -> 0 | AG44: =AA44+AF44 -> 0 | AH44: =$AH$34/$Z$86*AA44 -> #N/A | AI44: =AG44+AH44 -> #N/A | AJ44: =$AJ$34/$AF$86*AF44 -> #N/A | AK44: =AI44+AJ44 -> #N/A | AN44: =IF(AM44="Powering",O44) -> FALSE | AO44: =$AO$34 -> 0.01 | AP44: =AN44*AO44 -> 0 | AQ44: =AN44-AP44 -> 0
E45: kpl | F45: 1 | G45: =H45/F45 -> #N/A | H45: =AK45 -> #N/A | I45: 0 | N45: =L45*(1-M45) -> 0 | O45: =N45*F45 -> 0 | P45: 0,30 €/km | R45: {=_xlfn.IFS(P45=$P$28,$Q$28,P45=$P$26,Q45*$Q$26,P45=$P$27,Q45*$Q$27,P45=$P$25,Q45*$Q$25,P45=$P$29,$Q$29)} -> 0 | S45: =O45+R45 -> 0 | T45: 1 | V45: 0 | X45: =IF(W45=$W$27,$X$27,0)+IF(W45=$W$28,$X$28,0)+IF(W45=$W$29,$X$29,0) -> 0 | Y45: =X45*U45*V45*T45 -> 0 | Z45: =Y45*F45 -> 0 | AA45: =S45+Z45 -> 0 | AB45: 0.43 | AC45: =$AC$34 -> 0.01 | AD45: =S45*AB45 -> 0 | AE45: =Z45*AC45 -> 0 | AF45: =AD45+AE45 -> 0 | AG45: =AA45+AF45 -> 0 | AH45: =$AH$34/$Z$86*AA45 -> #N/A | AI45: =AG45+AH45 -> #N/A | AJ45: =$AJ$34/$AF$86*AF45 -> #N/A | AK45: =AI45+AJ45 -> #N/A | AN45: =IF(AM45="Powering",O45) -> FALSE | AO45: =$AO$34 -> 0.01 | AP45: =AN45*AO45 -> 0 | AQ45: =AN45-AP45 -> 0
E46: kpl | F46: 1 | G46: =H46/F46 -> #N/A | H46: =AK46 -> #N/A | I46: 0 | N46: =L46*(1-M46) -> 0 | O46: =N46*F46 -> 0 | P46: 0,30 €/km | R46: {=_xlfn.IFS(P46=$P$28,$Q$28,P46=$P$26,Q46*$Q$26,P46=$P$27,Q46*$Q$27,P46=$P$25,Q46*$Q$25,P46=$P$29,$Q$29)} -> 0 | S46: =O46+R46 -> 0 | T46: 1 | V46: 0 | X46: =IF(W46=$W$27,$X$27,0)+IF(W46=$W$28,$X$28,0)+IF(W46=$W$29,$X$29,0) -> 0 | Y46: =X46*U46*V46*T46 -> 0 | Z46: =Y46*F46 -> 0 | AA46: =S46+Z46 -> 0 | AB46: 0.43 | AC46: =$AC$34 -> 0.01 | AD46: =S46*AB46 -> 0 | AE46: =Z46*AC46 -> 0 | AF46: =AD46+AE46 -> 0 | AG46: =AA46+AF46 -> 0 | AH46: =$AH$34/$Z$86*AA46 -> #N/A | AI46: =AG46+AH46 -> #N/A | AJ46: =$AJ$34/$AF$86*AF46 -> #N/A | AK46: =AI46+AJ46 -> #N/A | AN46: =IF(AM46="Powering",O46) -> FALSE | AO46: =$AO$34 -> 0.01 | AP46: =AN46*AO46 -> 0 | AQ46: =AN46-AP46 -> 0
E47: kpl | F47: 1 | G47: =H47/F47 -> #N/A | H47: =AK47 -> #N/A | I47: 0 | N47: =L47*(1-M47) -> 0 | O47: =N47*F47 -> 0 | P47: 0,30 €/km | R47: {=_xlfn.IFS(P47=$P$28,$Q$28,P47=$P$26,Q47*$Q$26,P47=$P$27,Q47*$Q$27,P47=$P$25,Q47*$Q$25,P47=$P$29,$Q$29)} -> 0 | S47: =O47+R47 -> 0 | T47: 1 | V47: 0 | X47: =IF(W47=$W$27,$X$27,0)+IF(W47=$W$28,$X$28,0)+IF(W47=$W$29,$X$29,0) -> 0 | Y47: =X47*U47*V47*T47 -> 0 | Z47: =Y47*F47 -> 0 | AA47: =S47+Z47 -> 0 | AB47: 0.43 | AC47: =$AC$34 -> 0.01 | AD47: =S47*AB47 -> 0 | AE47: =Z47*AC47 -> 0 | AF47: =AD47+AE47 -> 0 | AG47: =AA47+AF47 -> 0 | AH47: =$AH$34/$Z$86*AA47 -> #N/A | AI47: =AG47+AH47 -> #N/A | AJ47: =$AJ$34/$AF$86*AF47 -> #N/A | AK47: =AI47+AJ47 -> #N/A | AN47: =IF(AM47="Powering",O47) -> FALSE | AO47: =$AO$34 -> 0.01 | AP47: =AN47*AO47 -> 0 | AQ47: =AN47-AP47 -> 0
... E71: kpl | F71: 1 | G71: =H71/F71 -> #N/A | H71: =AK71 -> #N/A | I71: 0 | N71: =L71*(1-M71) -> 0 | O71: =N71*F71 -> 0 | P71: 0,30 €/km | R71: {=_xlfn.IFS(P71=$P$28,$Q$28,P71=$P$26,Q71*$Q$26,P71=$P$27,Q71*$Q$27,P71=$P$25,Q71*$Q$25,P71=$P$29,$Q$29)} -> 0 | S71: =O71+R71 -> 0 | T71: 1 | V71: 0 | X71: =IF(W71=$W$27,$X$27,0)+IF(W71=$W$28,$X$28,0)+IF(W71=$W$29,$X$29,0) -> 0 | Y71: =X71*U71*V71*T71 -> 0 | Z71: =Y71*F71 -> 0 | AA71: =S71+Z71 -> 0 | AB71: 0.43 | AC71: =$AC$34 -> 0.01 | AD71: =S71*AB71 -> 0 | AE71: =Z71*AC71 -> 0 | AF71: =AD71+AE71 -> 0 | AG71: =AA71+AF71 -> 0 | AH71: =$AH$34/$Z$86*AA71 -> #N/A | AI71: =AG71+AH71 -> #N/A | AJ71: =$AJ$34/$AF$86*AF71 -> #N/A | AK71: =AI71+AJ71 -> #N/A | AN71: =IF(AM71="Powering",O71) -> FALSE | AO71: =$AO$34 -> 0.01 | AP71: =AN71*AO71 -> 0 | AQ71: =AN71-AP71 -> 0
D73: SINCLAIR | E73: =VLOOKUP(D73,'Cenník Sinclair '!$B$2:$D$43,3,FALSE) -> #N/A | F73: 1001 | G73: =H73/F73 -> #N/A | H73: =AK73 -> #N/A | I73: =AK73 -> #N/A | K73: =VLOOKUP(D73,'Cenník Sinclair '!$B$2:$F$101,5,FALSE) -> #N/A | L73: =VLOOKUP(D73,'Cenník Sinclair '!$B$2:$C$101,2,FALSE) -> #N/A | M73: =VLOOKUP(D73,'Cenník Sinclair '!$B$2:$E$101,4,FALSE) -> #N/A | N73: =L73*(1-M73) -> #N/A | O73: =N73*F73 -> #N/A | P73: 0,30 €/km | R73: {=_xlfn.IFS(P73=$P$28,$Q$28,P73=$P$26,Q73*$Q$26,P73=$P$27,Q73*$Q$27,P73=$P$25,Q73*$Q$25,P73=$P$29,$Q$29)} -> 0 | S73: =O73+R73 -> #N/A | T73: 1 | V73: 0 | X73: =IF(W73=$W$27,$X$27,0)+IF(W73=$W$28,$X$28,0)+IF(W73=$W$29,$X$29,0) -> 0 | Y73: =X73*U73*V73*T73 -> 0 | Z73: =Y73*F73 -> 0 | AA73: =S73+Z73 -> #N/A | AB73: =$AB$34 -> 0.3 | AC73: =$AC$34 -> 0.01 | AD73: =S73*AB73 -> #N/A | AE73: =Z73*AC73 -> 0 | AF73: =AD73+AE73 -> #N/A | AG73: =AA73+AF73 -> #N/A | AH73: =$AH$34/$Z$86*AA73 -> #N/A | AI73: =AG73+AH73 -> #N/A | AJ73: =$AJ$34/$AF$86*AF73 -> #N/A | AK73: =AI73+AJ73 -> #N/A | AN73: =IF(AM73="Powering",O73) -> FALSE | AO73: =$AO$34 -> 0.01 | AP73: =AN73*AO73 -> 0 | AQ73: =AN73-AP73 -> 0
D74: Hisense Easy CA25 Qch=2,6 kW vnútorná nástenná + vonkajšia | E74: =VLOOKUP(D74,cenniktoshiba!$B$3:$D190,3,FALSE) -> #N/A | F74: 1000 | G74: =H74/F74 -> #N/A | H74: =AK74 -> #N/A | I74: =AK74 -> #N/A | K74: =VLOOKUP(D74,cenniktoshiba!$B$3:$F190,5,FALSE) -> #N/A | L74: =VLOOKUP(D74,cenniktoshiba!$B$3:$C190,2,FALSE) -> #N/A | M74: =VLOOKUP(D74,cenniktoshiba!$B$3:$E190,4,FALSE) -> #N/A | N74: =L74*(1-M74) -> #N/A | O74: =N74*F74 -> #N/A | P74: 0,30 €/km | R74: {=_xlfn.IFS(P74=$P$28,$Q$28,P74=$P$26,Q74*$Q$26,P74=$P$27,Q74*$Q$27,P74=$P$25,Q74*$Q$25,P74=$P$29,$Q$29)} -> 0 | S74: =O74+R74 -> #N/A | T74: 1 | V74: 0 | X74: =IF(W74=$W$27,$X$27,0)+IF(W74=$W$28,$X$28,0)+IF(W74=$W$29,$X$29,0) -> 0 | Y74: =X74*U74*V74*T74 -> 0 | Z74: =Y74*F74 -> 0 | AA74: =S74+Z74 -> #N/A | AB74: =$AB$34 -> 0.3 | AC74: =$AC$34 -> 0.01 | AD74: =S74*AB74 -> #N/A | AE74: =Z74*AC74 -> 0 | AF74: =AD74+AE74 -> #N/A | AG74: =AA74+AF74 -> #N/A | AH74: =$AH$34/$Z$86*AA74 -> #N/A | AI74: =AG74+AH74 -> #N/A | AJ74: =$AJ$34/$AF$86*AF74 -> #N/A | AK74: =AI74+AJ74 -> #N/A | AM74: Powering | AN74: =IF(AM74="Powering",O74) -> #N/A | AO74: =$AO$34 -> 0.01 | AP74: =AN74*AO74 -> #N/A | AQ74: =AN74-AP74 -> #N/A
D75: Montáž klimatizácie | E75: kpl | F75: 1 | G75: =H75/F75 -> #N/A | H75: =AK75 -> #N/A | I75: 200 | L75: 135 | M75: 0 | N75: =L75*(1-M75) -> 135 | O75: =N75*F75 -> 135 | P75: 0,30 €/km | R75: {=_xlfn.IFS(P75=$P$28,$Q$28,P75=$P$26,Q75*$Q$26,P75=$P$27,Q75*$Q$27,P75=$P$25,Q75*$Q$25,P75=$P$29,$Q$29)} -> 0 | S75: =O75+R75 -> 135 | T75: 1 | V75: 0 | X75: =IF(W75=$W$27,$X$27,0)+IF(W75=$W$28,$X$28,0)+IF(W75=$W$29,$X$29,0) -> 0 | Y75: =X75*U75*V75*T75 -> 0 | Z75: =Y75*F75 -> 0 | AA75: =S75+Z75 -> 135 | AB75: 0 | AC75: =$AC$34 -> 0.01 | AD75: =S75*AB75 -> 0 | AE75: =Z75*AC75 -> 0 | AF75: =AD75+AE75 -> 0 | AG75: =AA75+AF75 -> 135 | AH75: =$AH$34/$Z$86*AA75 -> #N/A | AI75: =AG75+AH75 -> #N/A | AJ75: =$AJ$34/$AF$86*AF75 -> #N/A | AK75: =AI75+AJ75 -> #N/A | AN75: =IF(AM75="Powering",O75) -> FALSE | AO75: =$AO$34 -> 0.01 | AP75: =AN75*AO75 -> 0 | AQ75: =AN75-AP75 -> 0
D77: Drobný montážny materiál | E77: kpl | F77: 1 | G77: =H77/F77 -> #N/A | H77: =AK77 -> #N/A | I77: 20 | L77: 20 | N77: =L77*(1-M77) -> 20 | O77: =N77*F77 -> 20 | P77: 0,30 €/km | R77: {=_xlfn.IFS(P77=$P$28,$Q$28,P77=$P$26,Q77*$Q$26,P77=$P$27,Q77*$Q$27,P77=$P$25,Q77*$Q$25,P77=$P$29,$Q$29)} -> 0 | S77: =O77+R77 -> 20 | T77: 1 | V77: 0 | X77: =IF(W77=$W$27,$X$27,0)+IF(W77=$W$28,$X$28,0)+IF(W77=$W$29,$X$29,0) -> 0 | Y77: =X77*U77*V77*T77 -> 0 | Z77: =Y77*F77 -> 0 | AA77: =S77+Z77 -> 20 | AB77: 0 | AC77: =$AC$34 -> 0.01 | AD77: =S77*AB77 -> 0 | AE77: =Z77*AC77 -> 0 | AF77: =AD77+AE77 -> 0 | AG77: =AA77+AF77 -> 20 | AH77: =$AH$34/$Z$86*AA77 -> #N/A | AI77: =AG77+AH77 -> #N/A | AJ77: =$AJ$34/$AF$86*AF77 -> #N/A | AK77: =AI77+AJ77 -> #N/A | AN77: =IF(AM77="Powering",O77) -> FALSE | AO77: =$AO$34 -> 0.01 | AP77: =AN77*AO77 -> 0 | AQ77: =AN77-AP77 -> 0
D82: Potrubie Cu 6/10 x 0,8 Dual | E82: ks | F82: 5 | G82: =H82/F82 -> #N/A | H82: =AK82 -> #N/A | I82: =AK82 -> #N/A | K82: =VLOOKUP(D82,'Cenník Beijer Anmima'!$B$3:$G176,6,FALSE) -> Beijer | L82: =VLOOKUP(D82,'Cenník Beijer Anmima'!$B$2:$C$100,2,FALSE) -> 4.15 | M82: 0 | N82: =L82*(1-M82) -> 4.15 | O82: =N82*F82 -> 20.75 | P82: 0,30 €/km | R82: {=_xlfn.IFS(P82=$P$28,$Q$28,P82=$P$26,Q82*$Q$26,P82=$P$27,Q82*$Q$27,P82=$P$25,Q82*$Q$25,P82=$P$29,$Q$29)} -> 0 | S82: =O82+R82 -> 20.75 | T82: 1 | V82: 0 | X82: =IF(W82=$W$27,$X$27,0)+IF(W82=$W$28,$X$28,0)+IF(W82=$W$29,$X$29,0) -> 0 | Y82: =X82*U82*V82*T82 -> 0 | Z82: =Y82*F82 -> 0 | AA82: =S82+Z82 -> 20.75 | AB82: =$AB$34 -> 0.3 | AC82: =$AC$34 -> 0.01 | AD82: =S82*AB82 -> 6.225 | AE82: =Z82*AC82 -> 0 | AF82: =AD82+AE82 -> 6.225 | AG82: =AA82+AF82 -> 26.975 | AH82: =$AH$34/$Z$86*AA82 -> #N/A | AI82: =AG82+AH82 -> #N/A | AJ82: =$AJ$34/$AF$86*AF82 -> #N/A | AK82: =AI82+AJ82 -> #N/A | AN82: =IF(AM82="Powering",O82) -> FALSE | AO82: =$AO$34 -> 0.01 | AP82: =AN82*AO82 -> 0 | AQ82: =AN82-AP82 -> 0
D83: Žľab 60x45 mm + tvarovky | E83: ks | F83: 3 | G83: =H83/F83 -> #N/A | H83: =AK83 -> #N/A | I83: =AK83 -> #N/A | K83: =VLOOKUP(D83,'Cenník Beijer Anmima'!$B$3:$G177,6,FALSE) -> #N/A | L83: =VLOOKUP(D83,'Cenník Beijer Anmima'!$B$2:$C$100,2,FALSE) -> 2.86 | M83: 0 | N83: =L83*(1-M83) -> 2.86 | O83: =N83*F83 -> 8.58 | P83: 0,30 €/km | R83: {=_xlfn.IFS(P83=$P$28,$Q$28,P83=$P$26,Q83*$Q$26,P83=$P$27,Q83*$Q$27,P83=$P$25,Q83*$Q$25,P83=$P$29,$Q$29)} -> 0 | S83: =O83+R83 -> 8.58 | T83: 1 | V83: 0 | X83: =IF(W83=$W$27,$X$27,0)+IF(W83=$W$28,$X$28,0)+IF(W83=$W$29,$X$29,0) -> 0 | Y83: =X83*U83*V83*T83 -> 0 | Z83: =Y83*F83 -> 0 | AA83: =S83+Z83 -> 8.58 | AB83: =$AB$34 -> 0.3 | AC83: =$AC$34 -> 0.01 | AD83: =S83*AB83 -> 2.574 | AE83: =Z83*AC83 -> 0 | AF83: =AD83+AE83 -> 2.574 | AG83: =AA83+AF83 -> 11.154 | AH83: =$AH$34/$Z$86*AA83 -> #N/A | AI83: =AG83+AH83 -> #N/A | AJ83: =$AJ$34/$AF$86*AF83 -> #N/A | AK83: =AI83+AJ83 -> #N/A | AN83: =IF(AM83="Powering",O83) -> FALSE | AO83: =$AO$34 -> 0.01 | AP83: =AN83*AO83 -> 0 | AQ83: =AN83-AP83 -> 0
A84: 3 | B84: 3 | D84: Konzola na vonkajšiu jednotku | E84: ks | F84: 1 | I84: 55
I85: =SUM(I75:I84) -> #N/A
D86: Položky SPOLU | H86: =I86 -> #N/A | I86: =SUM(I75:I85) -> #N/A | N86: Materiál SPOLU | O86: =SUM(O35:O83) -> #N/A | P86: Doprava SPOLU | Q86: =SUM(R35:R83) -> 0 | R86: Dodávka SPOLU | S86: =O86+Q86 -> #N/A | W86: Montáž SPOLU | X86: =SUM(Z35:Z83) -> 0 | Y86: Náklady SPOLU | Z86: =S86+X86 -> #N/A | AA86: Zisk Dodávka | AB86: =SUM(AD35:AD83) -> #N/A | AC86: ZISK Montáž | AD86: =SUM(AE35:AE83) -> 0 | AE86: ZISK SPOLU | AF86: =AB86+AD86 -> #N/A | AI86: KONEČNÁ CENA BEZ DPH | AK86: =SUM(AK35:AK83) -> #N/A | AM86: SUM | AN86: =SUM(AN35:AN83) -> #N/A | AO86: =AO34 -> 0.01 | AP86: =SUM(AP35:AP83) -> #N/A | AQ86: =SUM(AQ35:AQ83) -> #N/A
K87: ZISK Dodávka | L87: =AB86 -> #N/A | M87: ZISK Montáž | N87: =AD86 -> 0 | O87: ZISK SPOLU | P87: =AF86 -> #N/A | Q87: Zisk + Rozpustený zisk SPOLU | S87: =$AF$86+$AJ$34 -> #N/A | X87: Náklady + Rozpustený náklad SPOLU | Z87: =Z86+AH34 -> #N/A | AD87: Zisk + Rozpustený zisk SPOLU | AF87: =$AF$86+$AJ$34 -> #N/A
D88: Spolu s DPH | I88: =I86*1.2 -> #N/A
C90: Cena zariadení a montáže | D90: Všetky neocenené položky budú v prípade potreby ocenené dodatočne.
C92: Termín dodania | D92: do 7 dní od potvrdenia objdnávky.
C95: Platobné podmienky | D95: Podľa dohody
C98: Platnosť ponuky: | D98: 60 dní.
C100: Záručná doba: | D100: Materiálová záruka 24 mesiacov od dodávky a za podmienky použitia originálnych náhradných dielov v prípade potreby. Záruka sa nevzťahuje na spotrebné náhradné diely.
C103: Podmienky platnosti záruky | D103: Servisné a montážne práce môže vykonávať iba firma zaškolená a certifikovaná na tento účel priamo výrobcom alebo zástupcom výrobcu.
D104: Používanie výhradne originálnych náhradných dielov.
D105: Vykonávanie pravidelných servisných prehliadok min 1x ročne autorizovanou servisnou firmou. Tieto prehliadky nie sú súčasťou CP, ale je to samostatne platená činnosť, ktorú si musí investor zabezpečiť na vlastné náklady.
C108: Záruka sa nevzťahuje | D108: Na spotrebné náhradné diely.
D109: Na škody a poruchy vzniknuté neodbornou alebo neautorizovanou obsluhou a manipuláciou.
D110: Na škody a poruchy vzniknuté neodborným alebo neautorizovaným servisným zásahom.
D111: Na škody vzniknuté prevádzkou zariadenia v podmienkach, ktoré sú v rozpore s prevádzkovými predpismi určenými výrobcom pre toto zariadenie.
D114: S pozdravom
D117: =D28 -> Mgr. Martin Holík
D118: =VLOOKUP(D117,'databáza KONTAKTY'!$B$1:$F$14,5,FALSE) -> Konateľ

Sheet Cenník Beijer Anmima
A1: P.č. | B1: MATERIÁL BEIJER ANMIMA | C1: Cenník | D1: Jednotka | E1: Cena z | F1: Aktualizované | G1: Dodávateľ
A2: 1 | B2: =IF($H$3>0,"Žľab 60x45 mm + tvarovky","Žľab 60x45 mm") -> Žľab 60x45 mm + tvarovky | C2: =2.2*(1+$H$3) -> 2.86 | D2: m | E2: 45331 | F2: 45331 | G2: Beijer | H2: Príplatok tvarovky
A3: 2 | B3: =IF($H$3>0,"Žľab 80x60 mm + tvarovky","Žľab 80x60 mm") -> Žľab 80x60 mm + tvarovky | C3: =3.3*(1+$H$3) -> 4.29 | D3: m | E3: 45331 | F3: 45331 | G3: Beijer | H3: =CP!M29 -> 0.3
A4: 3 | B4: =IF($H$3>0,"Žľab 110x75 mm + tvarovky","Žľab 110x75 mm") -> Žľab 110x75 mm + tvarovky | C4: =4.7*(1+$H$3) -> 6.11 | D4: m | E4: 45331 | F4: 45331 | G4: Beijer
A5: 4 | B5: Potrubie Cu 6/10 x 0,8 Dual | C5: 4.15 | D5: m | E5: 45331 | F5: 45331 | G5: Beijer
A6: 5 | B6: Potrubie Cu 6/12 x 0,8 Dual | C6: 5.25 | D6: m | E6: 45331 | F6: 45331 | G6: Beijer
A7: 6 | B7: Potrubie Cu 10/16 x 0,8 Dual | C7: 8.9 | D7: m | E7: 45405 | F7: 45405 | G7: Beijer
A8: 7 | B8: Potrubie Cu 6 x 0,8 Single | C8: 1.65 | D8: m | E8: 45331 | F8: 45331 | G8: Beijer
A9: 8 | B9: Potrubie Cu 10 x 0,8 Single | C9: 2.5 | D9: m | E9: 45331 | F9: 45331 | G9: Beijer
A10: 9 | B10: Potrubie Cu 12 x 0,8 Single | C10: 3.45 | D10: m | E10: 45331 | F10: 45331 | G10: Beijer
A11: 10 | B11: Potrubie Cu 16 x 1,0 Single | C11: 5.5 | D11: m | E11: 45331 | F11: 45331 | G11: Beijer
A12: 11 | B12: Potrubie Cu 22 x 1,0 Single | C12: 9.3 | D12: m | E12: 45331 | F12: 45331 | G12: Beijer
A13: 12 | B13: Hadica na kondenz 16 mm | C13: 0.48 | D13: m | E13: 45225 | F13: 45271 | G13: Beijer
A14: 13 | B14: Hadica na kondenz 20 mm | C14: 0.54 | D14: m | E14: 45238 | F14: 45271 | G14: Beijer
A15: 14 | B15: Spojka na hadicu 16 mm | C15: 1 | D15: ks | E15: 45159 | F15: 45271 | G15: Beijer
A16: 15 | B16: Kábel CYSY 3x1,5 | C16: 0.57 | D16: m | E16: 45133 | F16: 45271 | G16: Anmima
A17: 16 | B17: Kábel CYSY 3x2,5 | C17: 0.96 | D17: m | E17: 45125 | F17: 45271 | G17: Anmima
A18: 17 | B18: Kábel CYSY 3x4 | C18: 1.66 | D18: m | E18: 45306 | F18: 45306 | G18: Anmima | I18: https://www.aktaon.com/vodic-cysy-3x4-0-h05vv-f-p16515
A19: 18 | B19: Kábel CYSY 3x6 | C19: 3.33 | D19: m | E19: 45306 | F19: 45306 | G19: Anmima | I19: https://www.aktaon.com/vodic-cysy-3x6-0-h05vv-f-p16516
A20: 19 | B20: Kábel CYSY 5x2,5 | C20: 1.75 | D20: m | E20: 45306 | F20: 45306 | G20: Anmima | I20: https://www.aktaon.com/vodic-cysy-5x2-5-h05vv-f-p16529
A21: 20 | B21: Kábel CYKY-J 5x1,5 | C21: 0.78 | D21: m | E21: 45195 | F21: 45271 | G21: Anmima
A22: 21 | B22: Kábel CYKY-J 5x2,5 | C22: 1.49 | D22: m | E22: 45033 | F22: 45306 | G22: Anmima
A23: 22 | B23: Kábel JY(St)Y 1x2x0,8 | C23: 0.26 | D23: m | E23: 45264 | F23: 45271 | G23: Anmima
A24: 23 | B24: Kábel JY(St)Y 2x2x0,8 | C24: 0.36 | D24: m | E24: 45236 | F24: 45303 | G24: Anmima
A25: 24 | B25: Istič LTE 16C/1 6 kA (16 A) | C25: 4.26 | D25: ks | E25: 45035 | F25: 45303 | G25: Anmima
A26: 25 | B26: Istič LTE 20C/1 6 kA (20 A) | C26: 5.95 | D26: ks | E26: 45306 | F26: 45306 | G26: Anmima | I26: https://www.elektro-sychra.sk/istic-lte-20c-1-p789/
A27: 26 | B27: Istič LTE 25C/1 6 kA (25 A) | C27: 6.8 | D27: ks | E27: 45306 | F27: 45306 | G27: Anmima | I27: https://www.elektro-sychra.sk/oez-lte-25c-1-p6187/
A28: 27 | B28: Istič LTN 32C/1 6 kA (32 A) | C28: 11.57 | D28: ks | E28: 45306 | F28: 45306 | G28: Anmima | I28: https://www.elektro-sychra.sk/istic-ltn-32c-1-p801/
A29: 28 | B29: Istič LTE 16C/3 6 kA (16 A) | C29: 16.29 | D29: ks | E29: 45306 | F29: 45306 | G29: Anmima | I29: https://www.elektro-sychra.sk/istic-lte-16c-3-p849/
A30: 29 | B30: Istič LTE 32C/3 6 kA (32 A) | C30: 23.23 | D30: ks | E30: 45306 | F30: 45306 | G30: Anmima
A31: 30 | B31: Lišta LHD 20x20 mm | C31: 0.65 | D31: m | E31: 45223 | F31: 45271 | G31: Anmima
A32: 31 | B32: Lišta LHD 30x30 mm | C32: 0.77 | D32: m | E32: 45239 | F32: 45271 | G32: Anmima
A33: 32 | B33: Vidlica lomená | C33: 1.16 | D33: ks | E33: 45195 | F33: 45271 | G33: Anmima
A34: 33 | B34: Chladivo R32 | C34: 24 | D34: kg | E34: 45457 | F34: =E34 -> 45457 | G34: Beijer
A35: 34 | B35: Chladivo R410A | C35: 45 | D35: kg | E35: 45335 | F35: 45457 | G35: Beijer
A36: 35 | B36: Konzola na zem SP740 biela do 200 kg | C36: 29 | D36: ks | E36: cenník | F36: 45271 | G36: Beijer
A37: 36 | B37: Konzola na zem FFMINI čierna do 360 kg | C37: 89 | D37: ks | E37: cenník | F37: 45271 | G37: Beijer
A38: 37 | B38: Konzola na šikmú strechu | C38: 32 | D38: ks | E38: cenník | F38: 45344 | G38: Beijer

Sheet Cenník Powering 
A1: P.č. | B1: MATERIÁL POWERING | C1: Cenník | D1: Jednotka | E1: Zľava | F1: Dodávateľ
A2: 1 | B2: =IF($G$3>0,"Žľab 65x50 mm + tvarovky","Žľab 65x50 mm") -> Žľab 65x50 mm + tvarovky | C2: =5.74*(1+$G$3) -> 7.462 | D2: m | E2: 0.5 | F2: Powering | G2: Príplatok tvarovky
A3: 2 | B3: =IF($G$3>0,"Žľab 80x60 mm + tvarovky","Žľab 80x60 mm") -> Žľab 80x60 mm + tvarovky | C3: =6.32*(1+$G$3) -> 8.216 | D3: m | E3: 0.5 | F3: Powering | G3: =CP!M29 -> 0.3
A4: 3 | B4: =IF($G$3>0,"Žľab 90x65 mm + tvarovky","Žľab 90x65 mm") -> Žľab 90x65 mm + tvarovky | C4: =7.64*(1+$G$3) -> 9.932 | D4: m | E4: 0.5 | F4: Powering
A5: 4 | B5: Žľab 120x75 mm + tvarovky | C5: =14.92*(1+$G$3) -> 19.396 | D5: m | E5: 0.5 | F5: Powering
A6: 5 | B6: Potrubie Cu 6/10 x 0,8 Dual | C6: =4.48*2 -> 8.96 | D6: m | E6: 0.5 | F6: Powering
A7: 6 | B7: Potrubie Cu 6/12 x 0,8 Dual | C7: =5.6*2 -> 11.2 | D7: m | E7: 0.5 | F7: Powering
A8: 7 | B8: Potrubie Cu 6 x 0,8 Single | C8: =2*1.87 -> 3.74 | D8: m | E8: 0.5 | F8: Powering
A9: 8 | B9: Potrubie Cu 10 x 0,8 Single | C9: =2.78*2 -> 5.56 | D9: m | E9: 0.5 | F9: Powering
A10: 9 | B10: Potrubie Cu 12 x 0,8 Single | C10: =2*3.69 -> 7.38 | D10: m | E10: 0.5 | F10: Powering
A11: 10 | B11: Potrubie Cu 16 x 1,0 Single | C11: =6.22*2 -> 12.44 | D11: m | E11: 0.5 | F11: Powering
A12: 11 | B12: Hadica na kondenz 16 mm | C12: 0.96 | D12: m | E12: 0.5 | F12: Powering
A13: 12 | B13: Hadica na kondenz 18 mm | C13: 0.96 | D13: m | E13: 0.5 | F13: Powering
A14: 13 | B14: Hadica na kondenz 20 mm | C14: 1.08 | D14: m | E14: 0.5 | F14: Powering
A15: 14 | B15: Redukcia Y na kondenz | C15: 1.66 | D15: ks | E15: 0.5 | F15: Powering
A16: 15 | B16: Konzola 450 mm s vodováhou (80 kg) | C16: 25.66 | D16: ks | E16: 0.5 | F16: Powering
A17: 16 | B17: Konzola 450 mm s vodováhou (100 kg) | C17: 29.29 | D17: ks | E17: 0.5 | F17: Powering
A18: 17 | B18: Konzola 600 mm s vodováhou (160 kg) | C18: 44.06 | D18: ks | E18: 0.5 | F18: Powering
A19: 18 | B19: PVC podstavec 450 mm | C19: 15.78 | D19: ks | E19: 0.5 | F19: Powering
A20: 19 | B20: Podstavec z vulkanizovanej gumy 450 mm | C20: 44.54 | D20: ks | E20: 0.5 | F20: Powering
A21: 20 | B21: Podstavec z vulkanizovanej gumy 600 mm | C21: 73.78 | D21: ks | E21: 0.5 | F21: Powering
A22: 21 | B22: Silentbloky 48x20 mm set | C22: 4.8 | D22: ks | E22: 0.5 | F22: Powering
A23: 22 | B23: Káblový ovládač základný 120x120 mm + 10 m kábel | C23: 149 | D23: ks | E23: 0.5 | F23: Powering
... A40: 39 | B40: 3-cestný ventil so servopohonom | C40: 344 | D40: ks | E40: 0.5 | F40: Powering

Sheet Cenník VIVAX 
A1: P.č. | B1: VIVAX | C1: Cenník | D1: Jednotka | E1: Zľava | F1: Dodávateľ
A2: 1 | B2: Y-DESIGN | D2: ks | E2: 0.5 | F2: VIVAX | G2: Príplatok tvarovky
A3: 2 | B3: ACP-12CH35AEYIs R32 / I | C3: 1 462,10 € | D3: ks | E3: 0.5 | F3: VIVAX
A4: 3 | B4: ACP-12CH35AEYIs R32 / O | D4: ks | E4: 0.5 | F4: VIVAX
A5: 4 | B5: N-DESIGN | D5: ks | E5: 0.5 | F5: VIVAX
A6: 5 | B6: ACP-07CH21AEMI/I | C6: 216,36 € | D6: ks | E6: 0.5 | F6: VIVAX
A7: 6 | D7: ks | E7: 0.5 | F7: VIVAX
A8: 7 | B8: H+ DESIGN | D8: ks | E8: 0.5 | F8: VIVAX
A9: 8 | B9: Vnútorná | C9: (vrátane RP) | D9: ks | E9: 0.5 | F9: VIVAX
A10: 9 | B10: ACP-12CH35AEHI+ /I WHITE | C10: 982,37 € | D10: ks | E10: 0.5 | F10: VIVAX
A11: 10 | B11: ACP-12CH35AEHI+ R32 /O | D11: ks | E11: 0.5 | F11: VIVAX
A12: 11 | B12: ACP-12CH35AEHI+ /I SILVER | C12: 1 023,70 € | D12: ks | E12: 0.5 | F12: VIVAX
A13: 12 | B13: ACP-12CH35AEHI+ R32 /O | D13: ks | E13: 0.5 | F13: VIVAX
A14: 13 | B14: ACP-12CH35AEHI+/I GOLD | C14: 1 023,70 € | D14: ks | E14: 0.5 | F14: VIVAX
A15: 14 | B15: ACP-12CH35AEHI+ R32 /O | D15: ks | E15: 0.5 | F15: VIVAX
A16: 15 | B16: ACP-12CH35AEHI+ /I MIRROR | C16: 1 072,76 € | D16: ks | E16: 0.5 | F16: VIVAX
A17: 16 | B17: ACP-12CH35AEHI+ R32 /O | D17: ks | E17: 0.5 | F17: VIVAX
A18: 17 | B18: ACP-18CH50AEHI+ /I WHITE | C18: 1 279,40 € | D18: ks | E18: 0.5 | F18: VIVAX
A19: 18 | B19: ACP-18CH50AEHI+ R32 /O | D19: ks | E19: 0.5 | F19: VIVAX
A20: 19 | B20: ACP-18CH50AEHI+ /I SILVER | C20: 1 332,71 € | D20: ks | E20: 0.5 | F20: VIVAX
A21: 20 | B21: ACP-18CH50AEHI+ R32 /O | D21: ks | E21: 0.5 | F21: VIVAX
A22: 21 | B22: ACP-18CH50AEHI+ /I GOLD | C22: 1 332,71 € | D22: ks | E22: 0.5 | F22: VIVAX
A23: 22 | B23: ACP-18CH50AEHI+ R32 /O | D23: ks | E23: 0.5 | F23: VIVAX
A24: 23 | B24: ACP-18CH50AEHI+ /I MIRROR | C24: 1 394,77 € | D24: ks | E24: 0.5 | F24: VIVAX
A25: 24 | B25: ACP-18CH50AEHI+ R32 /O | D25: ks | E25: 0.5 | F25: VIVAX
A26: 25 | D26: ks | E26: 0.5 | F26: VIVAX
A27: 26 | B27: Vnútorná / vonkajšia jednotka | D27: ks | E27: 0.5 | F27: VIVAX
A28: 27 | B28: R+ DESIGN | D28: ks | E28: 0.5 | F28: VIVAX
A29: 28 | B29: ACP-09CH25AERI+ R32 / I | C29: 732.04 | D29: ks | E29: 0.5 | F29: VIVAX
A30: 29 | B30: ACP-09CH25AERI+ / O | D30: ks | E30: 0.5 | F30: VIVAX
A31: 30 | B31: ACP-09CH25AERI+ GOLD / | C31: 764.61 | D31: ks | E31: 0.5 | F31: VIVAX
A32: 31 | B32: ACP-09CH25AERI+ / O | D32: ks | E32: 0.5 | F32: VIVAX
A33: 32 | B33: ACP-09CH25AERI+ SILVER / I | C33: 764.61 | D33: ks | E33: 0.5 | F33: VIVAX
A34: 33 | B34: ACP-09CH25AERI+ / O | D34: ks | E34: 0.5 | F34: VIVAX
A35: 34 | B35: ACP-12CH35AERI+ R32 / I | C35: 762.34 | D35: ks | E35: 0.5 | F35: VIVAX
A36: 35 | B36: ACP-12CH35AERI+ / O | D36: ks | E36: 0.5 | F36: VIVAX
A37: 36 | B37: ACP-12CH35AERI+ GOLD / I | C37: 816.3 | D37: ks | E37: 0.5 | F37: VIVAX
A38: 37 | B38: ACP-12CH35AERI+ / O | D38: ks | E38: 0.5 | F38: VIVAX
A39: 38 | B39: ACP-12CH35AERI+ SILVER / I | C39: 816.3 | D39: ks | E39: 0.5 | F39: VIVAX
A40: 39 | B40: ACP-12CH35AERI+ / O | D40: ks | E40: 0.5 | F40: VIVAX
A41: 40 | B41: ACP-12CH35AERI+ MIRROR / I | C41: 816.3 | D41: ks | E41: 0.5 | F41: VIVAX
A42: 41 | B42: ACP-12CH35AERI+ | D42: ks | E42: 0.5 | F42: VIVAX
A43: 42 | B43: ACP-12CH35AERI+ RED / I | C43: 816.3 | D43: ks | E43: 0.5 | F43: VIVAX
A44: 43 | B44: ACP-12CH35AERI+ / O | D44: ks | E44: 0.5 | F44: VIVAX
A45: 44 | B45: ACP-18CH50AERI+ R32 / I | C45: 1167.9 | D45: ks | E45: 0.5 | F45: VIVAX
A46: 45 | B46: ACP-18CH50AERI+ | D46: ks | E46: 0.5 | F46: VIVAX
A47: 46 | B47: ACP-18CH50AERI+ MIRRO | D47: ks | E47: 0.5 | F47: VIVAX
A48: 47 | B48: ACP-18CH50AERI+ / O | C48: 1226.44 | D48: ks | E48: 0.5 | F48: VIVAX
A49: 48 | B49: ACP-24CH70AERI+ R32 / I | C49: 1568.7 | D49: ks | E49: 0.5 | F49: VIVAX
A50: 49 | B50: ACP-24CH70AERI+ | D50: ks | E50: 0.5 | F50: VIVAX
A51: 50 | D51: ks | E51: 0.5 | F51: VIVAX
A52: 51 | B52: M-DESIGN | D52: ks | E52: 0.5 | F52: VIVAX
A53: 52 | B53: ACP-09CH25AEMI+ R32 / I | C53: 599.86 | D53: ks | E53: 0.5 | F53: VIVAX
A54: 53 | B54: ACP-09CH25AEMI+ R32 / O | D54: ks | E54: 0.5 | F54: VIVAX
A55: 54 | B55: ACP-12CH35AEMI+ R32 / I | C55: 634.63 | D55: ks | E55: 0.5 | F55: VIVAX
A56: 55 | B56: ACP-12CH35AEMI+ R32 / O | D56: ks | E56: 0.5 | F56: VIVAX
A57: 56 | B57: ACP-18CH50AEMIs R32 / I | C57: 1002.54 | D57: ks | E57: 0.5 | F57: VIVAX
A58: 57 | B58: ACP-18CH50AEMIs R32 / O | D58: ks | E58: 0.5 | F58: VIVAX
A59: 58 | B59: ACP-24CH70AEMIs R32 / I | C59: 1348.86 | D59: ks | E59: 0.5 | F59: VIVAX
A60: 59 | B60: ACP-24CH70AEMIs R32 / O | D60: ks | E60: 0.5 | F60: VIVAX
A61: 60 | D61: ks | E61: 0.5 | F61: VIVAX
A62: 61 | B62: Q-DESIGN | D62: ks | E62: 0.5 | F62: VIVAX
A63: 62 | B63: ACP-09CH25AEQI+ R32 / I | C63: 577.46 | D63: ks | E63: 0.5 | F63: VIVAX
A64: 63 | B64: ACP-09CH25AEQI+ R32 / O | D64: ks | E64: 0.5 | F64: VIVAX
A65: 64 | B65: ACP-12CH35AEQI+ R32 / I | C65: 602.2 | D65: ks | E65: 0.5 | F65: VIVAX
A66: 65 | B66: ACP-12CH35AEQI+ R32 / O | D66: ks | E66: 0.5 | F66: VIVAX
A67: 66 | B67: ACP-18CH50AEQIs R32 / I | C67: 952.28 | D67: ks | E67: 0.5 | F67: VIVAX
A68: 67 | B68: ACP-18CH50AEQIs R32 / O | D68: ks | E68: 0.5 | F68: VIVAX
A69: 68 | B69: ACP-24CH70AEQIs R32 / I | C69: 1302.38 | D69: ks | E69: 0.5 | F69: VIVAX
A70: 69 | B70: ACP-24CH70AEQIs R32 / O | D70: ks | E70: 0.5 | F70: VIVAX
A71: 70 | D71: ks | E71: 0.5 | F71: VIVAX
A72: 71 | B72: Vnútorné nástenné jednotky R+ DESIG | D72: ks | E72: 0.5 | F72: VIVAX
A73: 72 | B73: ACP-09CH25AERI+/I WHITE | C73: 277.48 | D73: ks | E73: 0.5 | F73: VIVAX
A74: 73 | B74: ACP-09CH25AERI+/I GOLD | C74: 310.05 | D74: ks | E74: 0.5 | F74: VIVAX
A75: 74 | B75: ACP-09CH25AERI+/I SILVER | C75: 310.05 | D75: ks | E75: 0.5 | F75: VIVAX
A76: 75 | B76: ACP-12CH35AERI+/I WHITE | C76: 288.9 | D76: ks | E76: 0.5 | F76: VIVAX
A77: 76 | B77: ACP-12CH35AERI+/I GOLD | C77: 335.76 | D77: ks | E77: 0.5 | F77: VIVAX
A78: 77 | B78: ACP-12CH35AERI+/I SILVER | C78: 335.76 | D78: ks | E78: 0.5 | F78: VIVAX
A79: 78 | B79: ACP-12CH35AERI+/I MIRROR | C79: 335.76 | D79: ks | E79: 0.5 | F79: VIVAX
A80: 79 | B80: ACP-12CH35AERI+/I RED | C80: 335.76 | D80: ks | E80: 0.5 | F80: VIVAX
A81: 80 | B81: ACP-18CH50AERI+/I WHITE | C81: 408.28 | D81: ks | E81: 0.5 | F81: VIVAX
A82: 81 | B82: ACP-18CH50AERI+/I MIRROR | C82: 466.82 | D82: ks | E82: 0.5 | F82: VIVAX
A83: 82 | D83: ks | E83: 0.5 | F83: VIVAX
A84: 83 | B84: Vnútorné nástenné jednotky M-DESIG | D84: ks | E84: 0.5 | F84: VIVAX
A85: 84 | B85: ACP-07CH21AEMI/I | C85: 216.36 | D85: ks | E85: 0.5 | F85: VIVAX
A86: 85 | D86: ks | E86: 0.5 | F86: VIVAX
A87: 86 | B87: Vnútorné kazetové jednotky | D87: ks | E87: 0.5 | F87: VIVAX
A88: 87 | B88: ACP-09CC25AERI/I2 | C88: 547.56 | D88: ks | E88: 0.5 | F88: VIVAX
A89: 88 | B89: ACP-12CC35AERI/I3s | C89: 576.6 | D89: ks | E89: 0.5 | F89: VIVAX
A90: 89 | B90: ACP-18CC50AERI/I3s | C90: 628.25 | D90: ks | E90: 0.5 | F90: VIVAX
A91: 90 | D91: ks | E91: 0.5 | F91: VIVAX
A92: 91 | B92: Vnútorné parapetné jednotky | D92: ks | E92: 0.5 | F92: VIVAX
A93: 92 | B93: ACP-09CT25AERI/I3 | C93: 450.96 | D93: ks | E93: 0.5 | F93: VIVAX
A94: 93 | B94: ACP-12CT35AERI/I3 | C94: 484.82 | D94: ks | E94: 0.5 | F94: VIVAX
A95: 94 | B95: ACP-18CT50AERI/I3 | C95: 487.74 | D95: ks | E95: 0.5 | F95: VIVAX
A96: 95 | D96: ks | E96: 0.5 | F96: VIVAX
A97: 96 | B97: Vnútorné kanálové jednotky | D97: ks | E97: 0.5 | F97: VIVAX
A98: 97 | B98: ACP-12DT35AERI/I3s | C98: 637.08 | D98: ks | E98: 0.5 | F98: VIVAX
A99: 98 | B99: ACP-18DT50AERI/I3s | C99: 802.09 | D99: ks | E99: 0.5 | F99: VIVAX
A100: 99 | D100: ks | E100: 0.5 | F100: VIVAX
...

Sheet Cenník Sinclair 
A1: Pč | C1: Cena | D1: Jednotka | E1: Zľava | F1: Dodávateľ
B2: SPECTRUM PLUS SET INDOOR + OUTDOOR
A3: 1 | B3: ASH-09BIS2/W Nástenná klimatizácia SET | C3: 834 | D3: ks | E3: 0.49 | F3: SINCLAIR
A4: 2 | B4: ASH-13BIS2/W Nástenná klimatizácia SET | C4: 885 | D4: ks | E4: 0.49 | F4: SINCLAIR
A5: 3 | B5: ASH-18BIS2/W Nástenná klimatizácia SET | C5: 1 121 | D5: ks | E5: 0.49 | F5: SINCLAIR
A6: 4 | B6: ASH-24BIS2/W Nástenná klimatizácia SET | C6: 1 176 | D6: ks | E6: 0.49 | F6: SINCLAIR
A7: 5 | B7: TERREL SÉRIA SET INDOOR + OUTDOOR, WHITE PANEL
A8: 6 | B8: SIH-09BITx Terrel vnútorná jednotka | C8: 161.07 | D8: ks | E8: 0.49 | F8: SINCLAIR
A9: 7 | B9: SOH-09BIT Terrel Vonkajšia jednotka | C9: 262.08 | D9: ks | E9: 0.49 | F9: SINCLAIR
A10: 8 | B10: Cena Nástenná klimatizácia Terrel SET | C10: 423.15 | D10: ks | E10: 0.49 | F10: SINCLAIR
A11: 9 | B11: SIH-13BITx Terrel vnútorná jednotk | C11: 171.99 | D11: ks | E11: 0.49 | F11: SINCLAIR
A12: 10 | B12: SOH-13BIT Terrel Vonkajšia jednotka | C12: 278.46 | D12: ks | E12: 0.49 | F12: SINCLAIR
A13: 11 | B13: Cena Nástenná klimatizácia Terrel SET | C13: 450.45 | D13: ks | E13: 0.49 | F13: SINCLAIR
A14: 12 | B14: SIH-18BIT2x Terrel vnútorná jednotka | C14: 227.5 | D14: ks | E14: 0.49 | F14: SINCLAIR
A15: 13 | B15: SOH-18BIT2 Terrel Vonkajšia jednotka | C15: 491.4 | D15: ks | E15: 0.49 | F15: SINCLAIR
A16: 14 | B16: Cena Nástenná klimatizácia Terrel SET | C16: 718.9 | D16: ks | E16: 0.49 | F16: SINCLAIR
A17: 15 | B17: SIH-24BIT2x Terrel vnútorná jednotka | C17: 268.45 | D17: ks | E17: 0.49 | F17: SINCLAIR
A18: 16 | B18: SOH-24BIT2 Terrel Vonkajšia jednotka | C18: 586.95 | D18: ks | E18: 0.49 | F18: SINCLAIR
A19: 17 | B19: Cena Nástenná klimatizácia Terrel SET | C19: 855.4 | D19: ks | E19: 0.49 | F19: SINCLAIR
A20: 18 | B20: TERREL COLOR SÉRIA SET INDOOR + OUTDOOR, x options: S = Silver, B = Black, C = Champagne
A21: 19 | B21: SIH-09BITW Terrel vnútorná jednotka | C21: 161.07 | D21: ks | E21: 0.49 | F21: SINCLAIR
A22: 20 | B22: SOH-09BIT Terrel Vonkajšia jednotka | C22: 262.08 | D22: ks | E22: 0.49 | F22: SINCLAIR
A23: 21 | B23: Cena Nástenná klimatizácia Terrel SET | C23: 423.15 | D23: ks | E23: 0.49 | F23: SINCLAIR
A24: 22 | B24: SIH-13BITW Terrel vnútorná jednotk | C24: 171.99 | D24: ks | E24: 0.49 | F24: SINCLAIR
A25: 23 | B25: SOH-13BIT Terrel Vonkajšia jednotka | C25: 278.46 | D25: ks | E25: 0.49 | F25: SINCLAIR
A26: 24 | B26: Cena Nástenná klimatizácia Terrel SET | C26: 450.45 | D26: ks | E26: 0.49 | F26: SINCLAIR
A27: 25 | B27: SIH-18BIT2W Terrel vnútorná jednotka | C27: 227.5 | D27: ks | E27: 0.49 | F27: SINCLAIR
A28: 26 | B28: SOH-18BIT2 Terrel Vonkajšia jednotka | C28: 491.4 | D28: ks | E28: 0.49 | F28: SINCLAIR
A29: 27 | B29: Cena Nástenná klimatizácia Terrel SET | C29: 718.9 | D29: ks | E29: 0.49 | F29: SINCLAIR
A30: 28 | B30: SIH-24BIT2W Terrel vnútorná jednotka | C30: 268.45 | D30: ks | E30: 0.49 | F30: SINCLAIR
A31: 29 | B31: SOH-24BIT2 Terrel Vonkajšia jednotka | C31: 586.95 | D31: ks | E31: 0.49 | F31: SINCLAIR
A32: 30 | B32: Cena Nástenná klimatizácia Terrel SET | C32: 855.4 | D32: ks | E32: 0.49 | F32: SINCLAIR
A33: 31 | B33: MARVIN SÉRIA SET INDOOR + OUTDOOR
A34: 32 | B34: SIH-09BIMW vnútorná jednotka | C34: 182 | D34: ks | E34: 0.49 | F34: SINCLAIR | K34: y
A35: 33 | B35: SOH-09BIM Vonkajšia jednotka | C35: 303.03 | D35: ks | E35: 0.49 | F35: SINCLAIR
A36: 34 | B36: Cena Nástenná klimatizácia MARVIN SET | C36: 485.03 | D36: ks | E36: 0.49 | F36: SINCLAIR
A37: 35 | B37: SIH-12BIMW vnútorná jednotka | C37: 191.1 | D37: ks | E37: 0.49 | F37: SINCLAIR
A38: 36 | B38: SOH-12BIM Vonkajšia jednotka | C38: 324.87 | D38: ks | E38: 0.49 | F38: SINCLAIR
A39: 37 | B39: Cena Nástenná klimatizácia MARVIN SET | C39: 515.97 | D39: ks | E39: 0.49 | F39: SINCLAIR
A40: 38 | B40: SIH-18BIMW vnútorná jednotka | C40: 240.24 | D40: ks | E40: 0.49 | F40: SINCLAIR
A41: 39 | B41: SOH-18BIM Vonkajšia jednotka | C41: 550.55 | D41: ks | E41: 0.49 | F41: SINCLAIR
A42: 40 | B42: Cena Nástenná klimatizácia MARVIN SET | C42: 790.79 | D42: ks | E42: 0.49 | F42: SINCLAIR
A43: 41 | B43: SIH-24BIMW vnútorná jednotka | C43: 291.2 | D43: ks | E43: 0.49 | F43: SINCLAIR
A44: 42 | B44: SOH-24BIM Vonkajšia jednotka | C44: 645.19 | D44: ks | E44: 0.49 | F44: SINCLAIR
A45: 43 | B45: Cena Nástenná klimatizácia MARVIN SET | C45: 936.39 | D45: ks | E45: 0.49 | F45: SINCLAIR
A46: 44 | B46: MARVIN SÉRIA SET INDOOR + OUTDOOR x options: S = Silver, B = Black, C = Champagne | D46: ks | E46: 0.49 | F46: SINCLAIR
A47: 45 | B47: SIH-09BIMx | C47: 163.8 | D47: ks | E47: 0.49 | F47: SINCLAIR
A48: 46 | B48: SOH-09BIM | C48: 303.03 | D48: ks | E48: 0.49 | F48: SINCLAIR
A49: 47 | B49: Cena Nástenná klimatizácia MARVIN SET | C49: 466.83 | D49: ks | E49: 0.49 | F49: SINCLAIR
A50: 48 | B50: SIH-12BIMWx | C50: 171.99 | D50: ks | E50: 0.49 | F50: SINCLAIR
A51: 49 | B51: SOH-12BIM | C51: 324.87 | D51: ks | E51: 0.49 | F51: SINCLAIR
A52: 50 | B52: Cena Nástenná klimatizácia MARVIN SET | C52: 496.86 | D52: ks | E52: 0.49 | F52: SINCLAIR
A53: 51 | B53: SIH-18BIMWx | C53: 216.58 | D53: ks | E53: 0.49 | F53: SINCLAIR
A54: 52 | B54: SOH-18BIM | C54: 550.55 | D54: ks | E54: 0.49 | F54: SINCLAIR
A55: 53 | B55: Cena Nástenná klimatizácia MARVIN SET | C55: 767.13 | D55: ks | E55: 0.49 | F55: SINCLAIR
A56: 54 | B56: SIH-24BIMWx | C56: 262.08 | D56: ks | E56: 0.49 | F56: SINCLAIR
A57: 55 | B57: SOH-24BIM | C57: 645.19 | D57: ks | E57: 0.49 | F57: SINCLAIR
A58: 56 | B58: Cena Nástenná klimatizácia SET | C58: 907.27 | D58: ks | E58: 0.49 | F58: SINCLAIR
A59: 57 | B59: KEYON SÉRIA SET INDOOR + OUTDOOR | D59: ks | E59: 0.49 | F59: SINCLAIR
A60: 58 | B60: SIH-09BIK vnutorná jednotka | C60: 140.14 | D60: ks | E60: 0.49 | F60: SINCLAIR
A61: 59 | B61: SOH-09BIK2 vonkajšia jednotka | C61: 210.21 | D61: ks | E61: 0.49 | F61: SINCLAIR
A62: 60 | B62: Nástenná klimatizácia KEYON SET | C62: 350.35 | D62: ks | E62: 0.49 | F62: SINCLAIR
A63: 61 | B63: SIH-12BIK vnútorná jednotka | C63: 149.24 | D63: ks | E63: 0.49 | F63: SINCLAIR
A64: 62 | B64: SOH-12BIK2 vonkajšia jednotka | C64: 223.86 | D64: ks | E64: 0.49 | F64: SINCLAIR
A65: 63 | B65: Cena Nástenná klimatizácia KEYON SET 3,5kW | C65: 373.1 | D65: ks | E65: 0.49 | F65: SINCLAIR
A66: 64 | B66: SIH-18BIK vnútorná jednotka | C66: 200.2 | D66: ks | E66: 0.49 | F66: SINCLAIR
A67: 65 | B67: SOH-18BIK vonkajšia jednotka | C67: 370.37 | D67: ks | E67: 0.49 | F67: SINCLAIR
A68: 66 | B68: Cena Nástenná klimatizácia KEYON SET | C68: 570.57 | D68: ks | E68: 0.49 | F68: SINCLAIR
A69: 67 | B69: SIH-24BIK vnútorná jednotka | C69: 233.87 | D69: ks | E69: 0.49 | F69: SINCLAIR
A70: 68 | B70: SOH-24BIK vonkajšia jednotka | C70: 520.52 | D70: ks | E70: 0.49 | F70: SINCLAIR
A71: 69 | B71: Cena Nástenná klimatizácia KEYON SET | C71: 754.39 | D71: ks | E71: 0.49 | F71: SINCLAIR
A72: 70 | B72: SKY SÉRIA SET INDOOR + OUTDOOR | D72: ks | E72: 0.49 | F72: SINCLAIR
A73: 71 | B73: SIM-09BS-WF vnútorná jednotka | C73: 119.21 | D73: ks | E73: 0.49 | F73: SINCLAIR
A74: 72 | B74: SOM-09BS-LH vonkajšia jednotka | C74: 201.11 | D74: ks | E74: 0.49 | F74: SINCLAIR
A75: 73 | B75: Cena Nástenná klimatizácia SKY SET | C75: 320.32 | D75: ks | E75: 0.49 | F75: SINCLAIR
A76: 74 | B76: SIM-12BS-WFvnútorná jednotka | C76: 124.67 | D76: ks | E76: 0.49 | F76: SINCLAIR
A77: 75 | B77: SOM-12BS-LH vonkajšia jednotka | C77: 219.31 | D77: ks | E77: 0.49 | F77: SINCLAIR
A78: 76 | B78: Cena Nástenná klimatizácia SKY SET | C78: 343.98 | D78: ks | E78: 0.49 | F78: SINCLAIR
A79: 77 | B79: SIM-18BS-WF vnútorná jednotka | C79: 176.54 | D79: ks | E79: 0.49 | F79: SINCLAIR
A80: 78 | B80: SOM-18BS-LH vonkajšia jednotka | C80: 308.49 | D80: ks | E80: 0.49 | F80: SINCLAIR
A81: 79 | B81: Cena Nástenná klimatizácia SKY SET | C81: 485.03 | D81: ks | E81: 0.49 | F81: SINCLAIR
A82: 80 | B82: SOM-24BS-LH vonkajšia jednotka | C82: 206.57 | D82: ks | E82: 0.49 | F82: SINCLAIR
A83: 81 | B83: SOM-24BS-LH vonkajšia jednotka | C83: 420.42 | D83: ks | E83: 0.49 | F83: SINCLAIR
A84: 82 | B84: Cena Nástenná klimatizácia SKY SET | C84: 626.99 | D84: ks | E84: 0.49 | F84: SINCLAIR
A85: 83 | B85: SKY2 SÉRIA SET INDOOR + OUTDOOR | D85: ks | E85: 0.49 | F85: SINCLAIR
A86: 84 | B86: SIM-09BS2 vnútorná jednotka | C86: 121.03 | D86: ks | E86: 0.49 | F86: SINCLAIR
A87: 85 | B87: SOM-09BS2 vonkajšia jednotka | C87: 206.57 | D87: ks | E87: 0.49 | F87: SINCLAIR
A88: 86 | B88: Cena Nástenná klimatizácia SKY2 SET | C88: 327.6 | D88: ks | E88: 0.49 | F88: SINCLAIR
A89: 87 | B89: SIM-12BS2 vnútorná jednotka | C89: 143.78 | D89: ks | E89: 0.49 | F89: SINCLAIR
A90: 88 | B90: SOM-12BS2 vonkajšia jednotka | C90: 214.76 | D90: ks | E90: 0.49 | F90: SINCLAIR
A91: 89 | B91: Cena Nástenná klimatizácia SKY2 SET | C91: 358.54 | D91: ks | E91: 0.49 | F91: SINCLAIR
A92: 90 | B92: SIM-18BS2 vnútorná jednotka | C92: 189.28 | D92: ks | E92: 0.49 | F92: SINCLAIR
A93: 91 | B93: SOM-18BS2 vonkajšia jednotka | C93: 350.35 | D93: ks | E93: 0.49 | F93: SINCLAIR
A94: 92 | B94: Cena Nástenná klimatizácia SKY2 SET | C94: 539.63 | D94: ks | E94: 0.49 | F94: SINCLAIR
A95: 93 | B95: SIM-24BS2 vnútorná jednotka | C95: 221.13 | D95: ks | E95: 0.49 | F95: SINCLAIR
A96: 94 | B96: SOM-24BS2 vonkajšia jednotka | C96: 492.31 | D96: ks | E96: 0.49 | F96: SINCLAIR
A97: 95 | B97: Cena Nástenná klimatizácia SKY2 SET | C97: 713.44 | D97: ks | E97: 0.49 | F97: SINCLAIR
A98: 96 | B98: RAY SÉRIA SET INDOOR + OUTDOOR | D98: ks | E98: 0.49 | F98: SINCLAIR
A99: 97 | B99: SIH-09BIR vnútorná jednotka | C99: 119.21 | D99: ks | E99: 0.49 | F99: SINCLAIR
A100: 98 | B100: SOH-09BIR2 vonkajšia jednotka | C100: 201.11 | D100: ks | E100: 0.49 | F100: SINCLAIR
...

Sheet cenniktoshiba
A1: P.č. | B1: TOSHIBA | C1: Cenník | D1: Jednotka | E1: Zľava | F1: Dodávateľ
B2: KLIMATIZÁCIE RESIDENTIAL
A3: 1 | B3: Toshiba Seiya 07E2 Qch=2,0 kW vnútorná nástenná + vonkajšia | C3: 1210 | D3: ks | E3: 0.5 | F3: MSD Company
A4: 2 | B4: Toshiba Seiya 10E2 Qch=2,5 kW vnútorná nástenná + vonkajšia | C4: 1305 | D4: ks | E4: 0.5 | F4: MSD Company
A5: 3 | B5: Toshiba Seiya 13E2 Qch=3,5 kW vnútorná nástenná + vonkajšia | C5: 1415 | D5: ks | E5: 0.5 | F5: MSD Company
A6: 4 | B6: Toshiba Seiya 16E2 Qch=4,2 kW vnútorná nástenná + vonkajšia | C6: 1840 | D6: ks | E6: 0.5 | F6: MSD Company
A7: 5 | B7: Toshiba Seiya 18E2 Qch=5,0 kW vnútorná nástenná + vonkajšia | C7: 2195 | D7: ks | E7: 0.5 | F7: MSD Company
A8: 6 | B8: Toshiba Seiya 24E2 Qch=6,5 kW vnútorná nástenná + vonkajšia | C8: 2670 | D8: ks | E8: 0.5 | F8: MSD Company
A9: 7 | B9: Toshiba Shorai Edge 07J2 Qch=2,0 kW vnútorná nástenná + vonkajšia | C9: 1450 | D9: ks | E9: 0.5 | F9: MSD Company
A10: 8 | B10: Toshiba Shorai Edge 10J2 Qch=2,5 kW vnútorná nástenná + vonkajšia | C10: 1510 | D10: ks | E10: 0.5 | F10: MSD Company
A11: 9 | B11: Toshiba Shorai Edge 13J2 Qch=3,5 kW vnútorná nástenná + vonkajšia | C11: 1755 | D11: ks | E11: 0.5 | F11: MSD Company
A12: 10 | B12: Toshiba Shorai Edge 16J2 Qch=4,2 kW vnútorná nástenná + vonkajšia | C12: 2065 | D12: ks | E12: 0.5 | F12: MSD Company
A13: 11 | B13: Toshiba Shorai Edge 18J2 Qch=5,0 kW vnútorná nástenná + vonkajšia | C13: 2375 | D13: ks | E13: 0.5 | F13: MSD Company
A14: 12 | B14: Toshiba Shorai Edge 22J2 Qch=6,1 kW vnútorná nástenná + vonkajšia | C14: 2725 | D14: ks | E14: 0.5 | F14: MSD Company
... A35: 33 | B35: Toshiba Daisekai 9 16PK Qch=4,5 kW vnútorná nástenná + vonkajšia | C35: 3090 | D35: ks | E35: 0.5 | F35: MSD Company
A36: 34 | B36: Toshiba Seiya RAS-B07E2KVG-E vnútorná nástenná jednotka | C36: 273.6 | D36: ks | E36: 0.5 | F36: MSD Company | G36: =C36*0.8 -> 218.88
A37: 35 | B37: Toshiba Seiya RAS-B10E2KVG-E vnútorná nástenná jednotka | C37: 280.8 | D37: ks | E37: 0.5 | F37: MSD Company | G37: =C37*0.8 -> 224.64
A38: 36 | B38: Toshiba Seiya RAS-B13E2KVG-E vnútorná nástenná jednotka | C38: 288 | D38: ks | E38: 0.5 | F38: MSD Company | G38: =C38*0.8 -> 230.4
A39: 37 | B39: Toshiba Seiya RAS-B16E2KVG-E vnútorná nástenná jednotka | C39: 302.4 | D39: ks | E39: 0.5 | F39: MSD Company | G39: =C39*0.8 -> 241.92
A40: 38 | B40: Toshiba Shorai Edge RAS-B07G3KVSG-E vnútorná nástenná jednotka | C40: 496.8 | D40: ks | E40: 0.5 | F40: MSD Company
A41: 39 | B41: Toshiba Shorai Edge RAS-B10G3KVSG-E vnútorná nástenná jednotka | C41: 500.4 | D41: ks | E41: 0.5 | F41: MSD Company
A42: 40 | B42: Toshiba Shorai Edge RAS-B13G3KVSG-E vnútorná nástenná jednotka | C42: 536.4 | D42: ks | E42: 0.5 | F42: MSD Company
A43: 41 | B43: Toshiba Shorai Edge RAS-B16G3KVSG-E vnútorná nástenná jednotka | C43: 576 | D43: ks | E43: 0.5 | F43: MSD Company
A44: 42 | B44: Toshiba Shorai Edge RAS-B18G3KVSG-E vnútorná nástenná jednotka | C44: 612 | D44: ks | E44: 0.5 | F44: MSD Company
A45: 43 | B45: Toshiba Shorai Edge RAS-B22G3KVSG-E vnútorná nástenná jednotka | C45: 702 | D45: ks | E45: 0.5 | F45: MSD Company
A46: 44 | B46: Toshiba Shorai Edge RAS-B24G3KVSG-E vnútorná nástenná jednotka | C46: 820.8 | D46: ks | E46: 0.5 | F46: MSD Company
A47: 45 | B47: Toshiba Haori RAS-B10N4KVRG-E vnútorná nástenná jednotka | C47: 644.4 | D47: ks | E47: 0.5 | F47: MSD Company
A48: 46 | B48: Toshiba R32 RAS-2M14U2AVG-E 4kW vonkajšia jednotka | C48: =1917*0.8 -> 1533.6 | D48: ks | E48: 0.5 | F48: MSD Company
A49: 47 | B49: Toshiba R32 RAS-2M18U2AVG-E 5,2kW vonkajšia jednotka | C49: 1607.04 | D49: ks | E49: 0.5 | F49: MSD Company
A50: 48 | B50: Toshiba R32 RAS-3M18U2AVG-E 5,2kW vonkajšia jednotka | C50: 2185.92 | D50: ks | E50: 0.5 | F50: MSD Company
A51: 49 | B51: Toshiba R32 RAS-3M26U2AVG-E 7,5kW vonkajšia jednotka | C51: 2557.44 | D51: ks | E51: 0.5 | F51: MSD Company
A52: 50 | B52: Toshiba R32 RAS-4M27U2AVG-E 8kW vonkajšia jednotka | C52: 2950.56 | D52: ks | E52: 0.5 | F52: MSD Company
A53: 51 | B53: Toshiba R32 RAS-5M34U2AVG-E 10kW vonkajšia jednotka | C53: 3408.48 | D53: ks | E53: 0.5 | F53: MSD Company
A54: 52 | B54: Toshiba Outdoor unit, 4 kW HWT-401HW-E | C54: 1985 | D54: ks | E54: 0.5 | F54: MSD Company
A55: 53 | B55: Toshiba Outdoor unit, 6 kW HWT-601HW-E | C55: 2210 | D55: ks | E55: 0.5 | F55: MSD Company
A56: 54 | B56: Toshiba Outdoor unit, 8 kW HWT-801HW-E | C56: 3885 | D56: ks | E56: 0.5 | F56: MSD Company
A57: 55 | B57: Toshiba Outdoor unit, 8 kW, 3-phase HWT-801H8W-E | C57: 5275 | D57: ks | E57: 0.5 | F57: MSD Company
A58: 56 | B58: Toshiba Outdoor unit, 11 kW HWT-1101HW-E | C58: 4350 | D58: ks | E58: 0.5 | F58: MSD Company
A59: 57 | B59: Toshiba Outdoor unit, 11 kW, 3-phase HWT-1101H8W-E | C59: 5985 | D59: ks | E59: 0.5 | F59: MSD Company
A60: 58 | B60: Toshiba Outdoor unit, 14 kW HWT-1401HW-E | C60: 5510 | D60: ks | E60: 0.5 | F60: MSD Company
... A71: 62 | B71: Hisense AUD250 Qch=23,0 kW vnútorná kanálová + vonkajšia | C71: 6900 | D71: ks | E71: 0.45 | F71: Powering
B72: PARAPETNÉ/PODSTROPNÉ | E72: 0.45
A73: 63 | B73: Hisense AVT71 Qch=7,0 kW vnútorná parapetná/podstropná + vonkajšia | C73: 2368 | D73: ks | E73: 0.45 | F73: Powering
A74: 64 | B74: Hisense AUV105 Qch=9,5 kW vnútorná parapetná/podstropná + vonkajšia | C74: 3169 | D74: ks | E74: 0.45 | F74: Powering
A75: 65 | B75: Hisense AUV125 Qch=12,1 kW vnútorná parapetná/podstropná + vonkajšia | C75: 3876 | D75: ks | E75: 0.45 | F75: Powering
A76: 66 | B76: Hisense AUV140 Qch=13,5 kW vnútorná parapetná/podstropná + vonkajšia | C76: 4290 | D76: ks | E76: 0.45 | F76: Powering
A77: 67 | B77: Hisense AUV175 Qch=17,0 kW vnútorná parapetná/podstropná + vonkajšia | C77: 4559 | D77: ks | E77: 0.45 | F77: Powering
B78: KONZOLOVÉ | E78: 0.45
A79: 68 | B79: Hisense AKT26 Qch=2,6 kW vnútorná konzolová + vonkajšia | C79: 1373 | D79: ks | E79: 0.45 | F79: Powering
A80: 69 | B80: Hisense AKT35 Qch=3,5 kW vnútorná konzolová + vonkajšia | C80: 1452 | D80: ks | E80: 0.45 | F80: Powering
A81: 70 | B81: Hisense AKT52 Qch=4,9 kW vnútorná konzolová + vonkajšia | C81: 1855 | D81: ks | E81: 0.45 | F81: Powering
B82: TEPELNÉ ČERPADLÁ | E82: 0.45
A83: 71 | B83: TČ Hisense Split vonkajšia jednotka 4,4 kW | C83: 2107 | D83: ks | E83: 0.45 | F83: Powering
A84: 72 | B84: TČ Hisense Split vonkajšia jednotka 6,0 kW | C84: 2310 | D84: ks | E84: 0.45 | F84: Powering
A85: 73 | B85: TČ Hisense Split vonkajšia jednotka 8,0 kW | C85: 2538 | D85: ks | E85: 0.45 | F85: Powering
A86: 74 | B86: TČ Hisense Split vonkajšia jednotka 10,0 kW | C86: 3198 | D86: ks | E86: 0.45 | F86: Powering
A87: 75 | B87: TČ Hisense Split vonkajšia jednotka 12,0 kW | C87: 3350 | D87: ks | E87: 0.45 | F87: Powering
A88: 76 | B88: TČ Hisense Split vonkajšia jednotka 14,0 kW | C88: 3502 | D88: ks | E88: 0.45 | F88: Powering
A89: 77 | B89: TČ Hisense Split vonkajšia jednotka 16,0 kW | C89: 3629 | D89: ks | E89: 0.45 | F89: Powering
A90: 78 | B90: TČ Hisense Split Hydrobox pre 4,4 kW | C90: 2893 | D90: ks | E90: 0.45 | F90: Powering
A91: 79 | B91: TČ Hisense Split Hydrobox pre 6,0 kW | C91: 3198 | D91: ks | E91: 0.45 | F91: Powering
A92: 80 | B92: TČ Hisense Split Hydrobox pre 8,0 kW | C92: 3426 | D92: ks | E92: 0.45 | F92: Powering
A93: 81 | B93: TČ Hisense Split Hydrobox pre 10,0 kW | C93: 3705 | D93: ks | E93: 0.45 | F93: Powering
A94: 82 | B94: TČ Hisense Split Hydrobox pre 12,0 kW | C94: 3858 | D94: ks | E94: 0.45 | F94: Powering
... A109: 93 | B109: TČ Hisense Monoblok 16,0 kW | C109: 7360 | D109: ks | E109: 0.45 | F109: Powering

Sheet databáza KONTAKTY
B1: Bc. Mojmír Svoboda | C1: 421910907037 | D1: svoboda@edt.sk | F1: Servis manager
B2: Veronika Husárová | C2: 421905621661 | D2: servis.rozpocty@edt.sk
B3: Ing. Eduard Tuna | D3: etuna@edt.sk | F3: Director
B4: Ing. Matúš Derco | C4: 421911907027 | D4: derco@edt.sk | F4: Zákazkár
B5: Ing. Gejza Szabó | C5: 421915678958 | D5: szabo@edt.sk | F5: Sales manager for HVAC
B6: Ing. Andrej Majstrík | C6: 421911292442 | D6: majstrik@edt.sk | F6: Obchodný zástupca
B7: Mgr. Martin Holík | C7: 421902383121 | D7: holik@klimafresh.sk | F7: Konateľ
A9: Zákazník | B9: Kontaktná osoba | C9: t.č. | D9: e-mail | E9: adresa
A12: ABONUS s.r.o. | B12: Ing. Bohuslav Štepán | C12: 421905618689 | D12: bohuslav.stepan@abonus.com | E12: Pri strelnici 27 , Bratislava
A13: ABONUS s.r.o. | B13: Ing. Igor Silván | C13: 421905322793 | D13: igor.silvan@abonus.com | E13: Pri strelnici 27 , Bratislava
A14: ABONUS s.r.o. | B14: Jozef Sklenka | C14: 421918704637 | D14: jozef.sklenka@abonus.com | E14: Pri strelnici 27 , Bratislava
A15: ABONUS s.r.o. | B15: Jaroslav Žilavý | C15: 421905550033 | D15: jaroslav.zilavy@abonus.com | E15: Pri strelnici 27 , Bratislava
A16: Abas SR Managment | B16: Pavol Ondrovič | C16: 421910835203 | D16: facility.manager@abasco.sk | E16: Dúbravská cesta 1792/2C , Bratislava
A17: Adam Faljs | B17: Adam Flajs | C17: 421904919663 | D17: flajs.adam@gmail.com | E17: Bajkalská29E , Bratislava
A18: Adient Slovakia s.r.o. | B18: Marek Sojka | C18: 421907844094 | D18: marek.sojka@adient.com | E18: Mikušovská cesta 5363 , Lučenec | F18: JCI Lučenec
A19: Atos IT Solutions and Services s.r.o. | B19: Hudecová Dagmar | C19: 421903244640 | D19: dagmar.hudecova@atos.net | E19: Pribinova 19, Bratislava
A20: Adient Slovakia s.r.o. | B20: Julius Kantor | C20: 421918852137 | D20: julius.kantor@adient.com | E20: Mikušovská cesta 5363 , Lučenec | F20: JCI Lučenec
A21: Audiaplastics s.r.o. | B21: Radomír Telčík | C21: 421917444004 | D21: radomir.talcik@washpenn.com | E21: Voderady
A22: Audiaplastics s.r.o. | B22: Daniel Vypala | C22: 421918987821 | D22: daniel.vypala@washpenn.com | E22: Voderady
A23: Edita Aibekova | B23: p. Aibekova | C23: 421914108897 | D23: edita.aibekova@gmail.com | E23: Galanta
A24: Air Livery Limited , org.zl. | B24: Ing. Jozef Pojedinec | C24: 421905705769 | D24: pojedinec@viphandling.sk | E24: letisko M.R.Štefánika , Bratislava | F24: letisko MRŠtefánika
A25: AIRMARKET, s.r.o. | B25: Ján Mihala | C25: 421903421846 | D25: jan.mihala@gmail.com | E25: Jánošíková 2773/4A Nové Mesto nad Váhom | F25: projektant VZT
A26: AZ KLIMA SK, s.r.o | B26: Ing. Maroš Koník | C26: 421903265554 | D26: maros.konik@azklima.sk | E26: Nová Rožňavská 134/A, 831 04 Bratislava, Slovensko
A27: AZ KLIMA SK, s.r.o | B27: Radovan Knut | C27: 421903760874 | D27: radovan.knut@azklima.sk | E27: Nová Rožňavská 134/A, 831 04 Bratislava, Slovensko | F27: vedúci servisu
A28: BDI spol.s.r.o. | B28: Ing. Denisa Balkovská | C28: 421455240521 | D28: denisa.balkovska@dbi.sk | E28: T.G.Masaryka 9445/19, Zvolen
A29: BH ESTATE s.r.o. | B29: Jaroslav Haluška | C29: 33620030711 | D29: jlhcfr@gmail.com | E29: Landererova 6 , BA
A30: BILLA | B30: Ing. Ladislav Paško | C30: 421911067482 | D30: l.pasko@billa.sk | E30: Bajkalská 19/A , Bratislava
A31: BOCK SR s.r.o. | B31: Silvia Gelienová | C31: 421907707347 | D31: priprava@bocksr.sk | E31: Mostná 72, Nitra
A32: Cestné stavby Liptovský Mikuláš spol. s r.o. | B32: Tatiana Oravcová | C32: 421903400636 | D32: oravcova@cestnestavbylm.sk | E32: Ul. 1. mája 724, 031 01 Liptovský Mikuláš
A33: CRH Slovensko a.s. | B33: Ing. Aleš Pláteník | C33: 421903844588 | D33: ales.platenik@sk.crh.com | E33: Rohožník / Slovakia
A34: CRH Slovensko a.s. | B34: Dušan Rečný | C34: 421903269324 | D34: dusan.recny@sk.crh.com | E34: Rohožník / Slovakia
A35: CRH Slovensko a.s. | B35: Lubomír Ukropec | C35: 421903554622 | D35: lubomir.ukropec@sk.crh.com | E35: Rohožník / Slovakia
A36: CRH Slovensko a.s. | B36: Milan Fašánek | C36: 421903554676 | D36: milan.fasanek@sk.crh.com | E36: Rohožník / Slovakia
A37: CRH Slovensko a.s. | B37: Andrej Galbička | C37: 421902463365 | D37: andrej.galbicka@sk.crh.com | E37: Rohožník / Slovakia
A38: CRH Slovensko a.s. | B38: Tomáš Kainz | D38: tomas.kainz@sk.crh.com | E38: Rohožník / Slovakia
A39: Commerc service spol.s.r.o. | B39: Ľubica Surgentová | C39: 421517724344 | D39: loziska@commercservice.sk | E39: ku Surdoku 35 , 08001 Prešov | F39: Getragford správcovská
A40: Roman Dóza | B40: Roman Dóza | C40: 421904176107 | D40: dozaroman.mobil@gmail.com | E40: Stavbárska 40, Bratislava
A41: Spoločnosť Čínska reštaurácia, s.r.o. | B41: Ji | C41: 421902700628 | D41: info@cina-kuchajda.sk | E41: Tomašikova 55, Bratislava
A42: Deltech a.s. | B42: Ivan Šeucovič | C42: 421911889147 | D42: ivan.seucovic@deltech.sk | E42: Priemyselná 1, 031 01 Liptovský Mikuláš
A43: DSS Integra | B43: PaedDr. Renáta Balážová | C43: 421918826517 | D43: riaditel@dssintegra.sk | E43: Tylová 21, 831 04 Bratislava
A44: DSSI International LLC organizačná zložka | B44: Zuzana Pileková | C44: 421 2 32343029 | D44: zpilekova@directsourcing.com | E44: Turčianska 2 ,Blok F , 7. poschodie
A45: DIGI Slovakia s.r.o. | B45: Ľubomír Moravčík | C45: 421915992414 | D45: lubomir.moravcik@digislovakia.sk | E45: Röntgenova 26 , Bratislava
A46: DIGI Slovakia s.r.o. | B46: Ing. Silvia Strauchová | D46: silvia.strauchova@digislovakia.sk | E46: Röntgenova 26 , Bratislava
A47: Ericsson Slovensko spol.s.r.o. | B47: Tibor Markoš | C47: 421905965444 | D47: tibor.markos@ericsson.com | E47: Rožnavská 24 , Bratislava
A48: Ericsson Slovensko spol.s.r.o. | B48: Vladimír Kuna | D48: vladimir.kuna@ericsson.com | E48: Rožnavská 24 , Bratislava
A49: Ericsson Slovensko spol.s.r.o. | B49: Marta Papcová | C49: 421911407985 | D49: marta.papcova@ericsson.com | E49: Rožnavská 24 , Bratislava | F49: správa serverovní na Rožnavskej
A50: Ecoklima s.r.o. | B50: Martin Močko | C50: 421907247006 | D50: mocko@ecoklima.sk | E50: Vrbovská cesta 2511/19, Piešťany
A51: Ecoklima s.r.o. | B51: Lukáš Jurica | C51: 421907733561 | D51: manager@ecoklima.sk | E51: Vrbovská cesta 2511/19, Piešťany
A52: ENGIE Services a.s. | B52: Peter Mizner | C52: 421911266032 | D52: peter.mizner@engie.com | E52: Jarošova 1, 831 03 Bratislava | F52: Vedúci servisnej skupiny TZB
A53: Ernst Peter | B53: Ernst Peter | C53: 421905464098 | D53: ernst64@gmail.com | E53: Siladice
A54: Foxconn Slovakia spol.s.r.o. | B54: Ing. Jozef Sedliak | C54: 421905617812 | D54: jozef.sedliak@emea.foxconn.com | E54: Dolné Hony 29 , Nitra
A55: Gemeri Ondrej | B55: Ondrej Gemeri | C55: 421908518133 | D55: o.gemeri@gmail.com | E55: Nová 877, Dolná Streda
A56: Global Facility a.s. | B56: Daniel Bezák | C56: 421948466580 | D56: bezak@globalfacility.sk | E56: Račianska 153 , Bratislava | F56: Predseda predstavenstva
A57: Golden Shine trading s. r. o. | B57: Stefan | C57: 421911122659 | D57: r.golden10@gmail.com | E57: Papraďová 1/A, 821 01 Bratislava
A58: GreMi KLIMA, s.r.o. | B58: Ing. Jakub Kučerík | C58: 421948719840 | D58: jakub.kucerik@gremi.com | E58: Kragujevská 9, SK-010 01 Žilina | F58: projektant VZT
A59: HB REM spol.s.r.o. | B59: Mgr. Radovan Macháč | C59: 421905451733 | D59: radovan.machac@hbreavis.com | E59: Karadžičova 12 , Bratislava
A60: HORVÁT klimatizácia a vetranie, s.r.o. | B60: Dušan Gráč | C60: 421911514778 | D60: grac@horvat.sk | E60: Bánovská cesta 11, 010 01 Žilina
A61: Inštitút VS MV SR | B61: Tibor Beneš | C61: 421917834401 | D61: eko@vsmv.sk | E61: Azalkova 5 ,Bratislava
A62: I.T.A TELECOM SLOVAKIA, s.r.o. | B62: Lukáš Valent | C62: 421918915869 | D62: lukas.valent@ita-telecom.sk | E62: Nové Záhrady I 13/a
A63: I.T.A TELECOM SLOVAKIA, s.r.o. | B63: Eric Vattier | C63: 421903907152 | D63: eric.vattier@ita-telecom.sk | E63: Nové Záhrady I 13/a
A64: Justičná akadémia Slovenskej republiky | B64: Peter Psota | C64: 421905872466 | D64: peter.psota@justice.sk | E64: Suvorovova 5/C, 902 01 Pezinok
A65: J&L Construction s.r.o | B65: Jaroslav Haluška | C65: 33620030711 | D65: jlhcfr@gmail.com | E65: Nadbrežna 5/8 Moravany
A66: LEYUAN, s.r.o. | C66: 421902700628 | D66: info@cina-kuchajda.sk | E66: Tomašikova 55, Bratislava
A67: Jana Dracová | B67: Jana Dracová | C67: 421907921027 | D67: janadracova@gmail.com | E67: Čajaková 4030/7, Bratislava
A68: J & T REAL ESTATE, a.s. | B68: Pieš | D68: pies@jtre.sk | E68: Dvořákovo nábrežie 10 811 02 Bratislava
A69: Oľga Jacová | B69: Oľga Jacová | C69: 421904301077 | D69: jacovaolga@gmail.com | E69: Branč
A70: KLIMA TREND , spol.s.r.o. | B70: Ing. Tomáš Košík | C70: 421911707031 | D70: kosikt@klimatrend.sk | E70: Štúrova 165 , Nitra 949 01
A71: KLIMA TREND , spol.s.r.o. | B71: Ing. Mario Sýkora | C71: 421910919686 | D71: sykora@klimatrend.sk | E71: Štúrova 165 , Nitra 949 01
A72: KLIMAK, s.r.o. | B72: Ing. Branislav Pauk | C72: 421911707047 | D72: pauk@klimakslovakia.com | E72: Štúrová 165, Nitra 949 01
A73: Klimaservis Bratislava s.r.o. | B73: Dušan Uriča | C73: 421905409187 | D73: dusan.urica@klimaservisba.sk | E73: Domašská 10 , Bratislava
A74: Klimaservis Bratislava s.r.o. | B74: Zuzana Schniererová | C74: 421905990195 | D74: zuzana.schniererova@klimaservisba.sk | E74: Domašská 10 , Bratislava
A75: KlimaVal s.r.o. | B75: Martin Valenčin | C75: 421905924038 | D75: firma@klimaval.sk | E75: Pod Táborom 12918/45, Prešov
A76: Krajský súd v Bratislave | B76: Bruno Siebenstich | C76: 421903237100 | D76: bruno.siebenstich@justice.sk | E76: Záhradnícka 10, 813 66 Bratislava
A77: Krkoš Miroslav | B77: Miroslav Krkoš | C77: 421914338450 | D77: miroslav.krkos@citi.com | E77: Odbojárov 8, Bratislava
A78: Ivan Kršák | B78: Ivan Kršák | C78: 421903205169 | D78: krsotn@zoznam.sk
A79: Kubiczová | B79: Kubiczová | C79: 421903766149 | D79: kubimasro@gmail.com | E79: Kremelská 77, 84110 Bratislava, Devín
A80: Lightstorm Communications s.r.o. | B80: Tomáš Molota | C80: 421903788100 | D80: tomas.molota@lightstorm.sk | E80: Páričkova 18 , Bratislava
A81: Tomaš Cagáň | B81: Tomáš Cagaň | C81: 421905706665 | D81: cagan.tomas@gmail.com | E81: Ludovíta Fullu 56, Bratislava
A82: Luboš Kovár | B82: Jana Hakoci | C82: 421948902972 | D82: jana.hakoci@gmail.com | E82: Žltá 4, 851 07 Bratislava
A83: Lightstorm Communications s.r.o. | B83: Peter Schill | C83: 421903448623 | D83: peter.schill@lightstorm.sk | E83: Páričkova 18 , Bratislava
A84: Magistrát hlavného mesta SR Bratislavy | B84: Ing. Vladimír Zdražil | C84: 421903985958 | D84: vladimir.zdrazil@bratislava.sk | E84: Primaciálne námestie 1, 814 99 Bratislava | F84: vedúci technického referátu
A85: Magna PT s.r.o. | B85: Ľuboš Porubský | C85: 421556148509 | D85: lubos.porubsky@magna.com | E85: Perínska cesta 282 , Kechnec
A86: Majer Marek | B86: Marek Majer | C86: 421911801450 | D86: mmarecekk@centrum.sk | E86: Kolónia 607, Lehnice
A87: Marian Kubánek | B87: Marian Kubánek | C87: 421908710539 | D87: marian.kubanek@gmail.com | E87: Rozmarínova 35 ,Bratislava
A88: Michalovích Dominika | B88: Dominika Michalovích | C88: 421902700628 | D88: dominika.michalovich@gmail.com | E88: Okružná 149, Slovenský Grob
A89: Dušan Šoltes | B89: Šoltes | E89: Dvanásta 9, Bratislava
A90: Motor Car Bratislava spol. s.r.o. | B90: Ji | C90: 421918424050 | D90: i.seemannova@motor-car.sk | E90: Tuhovská 5 , Bratislava
A91: Motor Car Bratislava spol. s r.o. | B91: Peter Hrašna | C91: 421918766265 | D91: p.hrasna@motor-car.sk | E91: Tuhovská 5 , Bratislava
A92: Motor Car Bratislava spol. s r.o. | B92: Dominika Ďuránová | C92: 421907245641 | D92: d.duranova@motor-car.sk | E92: Tuhovská 5 , Bratislava
A93: Motor Car Bratislava spol. s.r.o. | B93: Patrícia Kubusová | C93: 421918424322 | D93: p.kubusova@motor-car.sk | E93: Tuhovská 5 , Bratislava
A94: MERAX SK s.r.o. | B94: Marian Čermák | C94: 421903726925 | D94: merax@merax.sk | E94: Kpt. Nálepku 102 , 934 01 Levice
A95: m-plan, s.r.o. | B95: Ing. Marek Blaho | C95: 421908449581 | D95: blaho@mplan.sk | E95: Rybničná 40, Bratislava
A96: MSD Company s.r.o. | B96: Ing. Richard Maček | C96: 421905724096 | D96: macek@msdcompany.sk | E96: Nádražná 50, Ivanka pri Dunaji | F96: project manager
A97: Národná banka Slovenska | B97: Lubor Vitek | C97: 421915720059 | D97: lubor.vitek@nbs.sk | E97: Imricha Karvaša 1 , Bratislava
A98: Národná banka Slovenska | B98: Dušan Zvač | C98: 421918720388 | D98: dusan.zvac@nbs.sk | E98: Imricha Karvaša 1 , Bratislava
A99: NBI s.r.o. | B99: Nikita Balašov | C99: 421220902788 | D99: nbi@nbi.sk | E99: Mliekarenská 19m, 821 09 Bratislava
A100: Neibrs s.r.o. | B100: Rastislav Nemčík | C100: 421915365743 | D100: nemcik@neibrs.sk | E100: Dulovo nám. - Páričkova 29, 821 08 Bratislava
A101: Niersberger Slovakia , s.r.o. | B101: Ing. Martin Škvarka | C101: 421915811819 | D101: skvarka@niersberger.sk | E101: Bytčická cesta 82 , Žilina
A102: Niersberger Slovakia , s.r.o. | B102: Marian Raffaj | C102: 421915811806 | D102: raffaj@niersberger.sk | E102: Bytčická cesta 82 , Žilina
A103: Niersberger Slovakia , s.r.o. | B103: Peter Lajčok | C103: 421915811821 | D103: lajcok@niersberger.sk | E103: Bytčická cesta 82 , Žilina
...

Sheet Cenník Mitsubishi
A1: P.č. | B1: MITSUBISHI | C1: Cenník | D1: Jednotka | E1: Zľava | F1: Dodávateľ
B2: KLIMATIZÁCIE RESIDENTIAL
A3: 1 | B3: Mitsubishi Economy HR25 Qch=2,5 kW vnútorná nástenná + vonkajšia | C3: 820 | D3: ks | E3: 0.39 | F3: CS-Mtrade
A4: 2 | B4: Mitsubishi Economy HR35 Qch=3,5 kW vnútorná nástenná + vonkajšia | C4: 944 | D4: ks | E4: 0.39 | F4: CS-Mtrade
A5: 3 | B5: Mitsubishi Economy HR35 Qch=5,0 kW vnútorná nástenná + vonkajšia | C5: 1228 | D5: ks | E5: 0.39 | F5: CS-Mtrade
A6: 4 | B6: Mitsubishi Standard AP20 Qch=2,0 kW vnútorná nástenná + vonkajšia | C6: 1237 | D6: ks | E6: 0.39 | F6: CS-Mtrade
A7: 5 | B7: Mitsubishi Standard AY25 Qch=2,5 kW vnútorná nástenná + vonkajšia | C7: 1304 | D7: ks | E7: 0.39 | F7: CS-Mtrade
A8: 6 | B8: Mitsubishi Standard AY35 Qch=3,5 kW vnútorná nástenná + vonkajšia | C8: 1502 | D8: ks | E8: 0.39 | F8: CS-Mtrade
A9: 7 | B9: Mitsubishi Standard AY42 Qch=4,2 kW vnútorná nástenná + vonkajšia | C9: 1590 | D9: ks | E9: 0.39 | F9: CS-Mtrade
A10: 8 | B10: Mitsubishi Standard AY50 Qch=5,0 kW vnútorná nástenná + vonkajšia | C10: 1704 | D10: ks | E10: 0.39 | F10: CS-Mtrade
A11: 9 | B11: Mitsubishi Standard AP60 Qch=6,1 kW vnútorná nástenná + vonkajšia | C11: 1929 | D11: ks | E11: 0.39 | F11: CS-Mtrade
A12: 10 | B12: Mitsubishi Standard AP70 Qch=7,1 kW vnútorná nástenná + vonkajšia | C12: 2369 | D12: ks | E12: 0.39 | F12: CS-Mtrade
A13: 11 | B13: Mitsubishi Premium EF25 Qch=2,5 kW vnútorná nástenná biela + vonkajšia | C13: 1547 | D13: ks | E13: 0.39 | F13: CS-Mtrade
A14: 12 | B14: Mitsubishi Premium EF35 Qch=3,5 kW vnútorná nástenná biela + vonkajšia | C14: 1842 | D14: ks | E14: 0.39 | F14: CS-Mtrade
... A40: 38 | B40: Mitsubishi Diamond LN60 Qch=6,1 kW vnútorná nástenná prírodná biela + vonkajšia | C40: 3156 | D40: ks | E40: 0.39 | F40: CS-Mtrade

Sheet vivax
A1: Stĺpec1 | B1: Stĺpec2 | C1: Stĺpec3 | D1: Stĺpec4 | E1: Stĺpec5 | F1: Stĺpec6
A2: P.č. | B2: VIVAX | C2: Cenník | D2: Jednotka | E2: Zľava | F2: Dodávateľ
A3: 1 | B3: Y-DESIGN | D3: ks | E3: 0.5 | F3: VIVAX
A4: 2 | B4: ACP-12CH35AEYIs R32 / I | C4: 1 462,10 € | D4: ks | E4: 0.5 | F4: VIVAX
A5: 3 | B5: ACP-12CH35AEYIs R32 / O | D5: ks | E5: 0.5 | F5: VIVAX
A6: 4 | B6: N-DESIGN | D6: ks | E6: 0.5 | F6: VIVAX
A7: 5 | B7: ACP-07CH21AEMI/I | C7: 216,36 € | D7: ks | E7: 0.5 | F7: VIVAX
A8: 6 | D8: ks | E8: 0.5 | F8: VIVAX
A9: 7 | B9: H+ DESIGN | D9: ks | E9: 0.5 | F9: VIVAX
A10: 8 | B10: Vnútorná | C10: (vrátane RP) | D10: ks | E10: 0.5 | F10: VIVAX
A11: 9 | B11: ACP-12CH35AEHI+ /I WHITE | C11: 982,37 € | D11: ks | E11: 0.5 | F11: VIVAX
A12: 10 | B12: ACP-12CH35AEHI+ R32 /O | D12: ks | E12: 0.5 | F12: VIVAX
A13: 11 | B13: ACP-12CH35AEHI+ /I SILVER | C13: 1 023,70 € | D13: ks | E13: 0.5 | F13: VIVAX
A14: 12 | B14: ACP-12CH35AEHI+ R32 /O | D14: ks | E14: 0.5 | F14: VIVAX
A15: 13 | B15: ACP-12CH35AEHI+/I GOLD | C15: 1 023,70 € | D15: ks | E15: 0.5 | F15: VIVAX
A16: 14 | B16: ACP-12CH35AEHI+ R32 /O | D16: ks | E16: 0.5 | F16: VIVAX
A17: 15 | B17: ACP-12CH35AEHI+ /I MIRROR | C17: 1 072,76 € | D17: ks | E17: 0.5 | F17: VIVAX
A18: 16 | B18: ACP-12CH35AEHI+ R32 /O | D18: ks | E18: 0.5 | F18: VIVAX
A19: 17 | B19: ACP-18CH50AEHI+ /I WHITE | C19: 1 279,40 € | D19: ks | E19: 0.5 | F19: VIVAX
A20: 18 | B20: ACP-18CH50AEHI+ R32 /O | D20: ks | E20: 0.5 | F20: VIVAX
A21: 19 | B21: ACP-18CH50AEHI+ /I SILVER | C21: 1 332,71 € | D21: ks | E21: 0.5 | F21: VIVAX
A22: 20 | B22: ACP-18CH50AEHI+ R32 /O | D22: ks | E22: 0.5 | F22: VIVAX
A23: 21 | B23: ACP-18CH50AEHI+ /I GOLD | C23: 1 332,71 € | D23: ks | E23: 0.5 | F23: VIVAX
A24: 22 | B24: ACP-18CH50AEHI+ R32 /O | D24: ks | E24: 0.5 | F24: VIVAX
A25: 23 | B25: ACP-18CH50AEHI+ /I MIRROR | C25: 1 394,77 € | D25: ks | E25: 0.5 | F25: VIVAX
A26: 24 | B26: ACP-18CH50AEHI+ R32 /O | D26: ks | E26: 0.5 | F26: VIVAX
A27: 25 | D27: ks | E27: 0.5 | F27: VIVAX
A28: 26 | B28: Vnútorná / vonkajšia jednotka | D28: ks | E28: 0.5 | F28: VIVAX
A29: 27 | B29: R+ DESIGN | D29: ks | E29: 0.5 | F29: VIVAX
A30: 28 | B30: ACP-09CH25AERI+ R32 / I | C30: 732.04 | D30: ks | E30: 0.5 | F30: VIVAX
A31: 29 | B31: ACP-09CH25AERI+ / O | D31: ks | E31: 0.5 | F31: VIVAX
A32: 30 | B32: ACP-09CH25AERI+ GOLD / | C32: 764.61 | D32: ks | E32: 0.5 | F32: VIVAX
A33: 31 | B33: ACP-09CH25AERI+ / O | D33: ks | E33: 0.5 | F33: VIVAX
A34: 32 | B34: ACP-09CH25AERI+ SILVER / I | C34: 764.61 | D34: ks | E34: 0.5 | F34: VIVAX
A35: 33 | B35: ACP-09CH25AERI+ / O | D35: ks | E35: 0.5 | F35: VIVAX
A36: 34 | B36: ACP-12CH35AERI+ R32 / I | C36: 762.34 | D36: ks | E36: 0.5 | F36: VIVAX
A37: 35 | B37: ACP-12CH35AERI+ / O | D37: ks | E37: 0.5 | F37: VIVAX
A38: 36 | B38: ACP-12CH35AERI+ GOLD / I | C38: 816.3 | D38: ks | E38: 0.5 | F38: VIVAX
A39: 37 | B39: ACP-12CH35AERI+ / O | D39: ks | E39: 0.5 | F39: VIVAX
A40: 38 | B40: ACP-12CH35AERI+ SILVER / I | C40: 816.3 | D40: ks | E40: 0.5 | F40: VIVAX
A41: 39 | B41: ACP-12CH35AERI+ / O | D41: ks | E41: 0.5 | F41: VIVAX
A42: 40 | B42: ACP-12CH35AERI+ MIRROR / I | C42: 816.3 | D42: ks | E42: 0.5 | F42: VIVAX
A43: 41 | B43: ACP-12CH35AERI+ | D43: ks | E43: 0.5 | F43: VIVAX
A44: 42 | B44: ACP-12CH35AERI+ RED / I | C44: 816.3 | D44: ks | E44: 0.5 | F44: VIVAX
A45: 43 | B45: ACP-12CH35AERI+ / O | D45: ks | E45: 0.5 | F45: VIVAX
A46: 44 | B46: ACP-18CH50AERI+ R32 / I | C46: 1167.9 | D46: ks | E46: 0.5 | F46: VIVAX
A47: 45 | B47: ACP-18CH50AERI+ | D47: ks | E47: 0.5 | F47: VIVAX
A48: 46 | B48: ACP-18CH50AERI+ MIRRO | D48: ks | E48: 0.5 | F48: VIVAX
A49: 47 | B49: ACP-18CH50AERI+ / O | C49: 1226.44 | D49: ks | E49: 0.5 | F49: VIVAX
A50: 48 | B50: ACP-24CH70AERI+ R32 / I | C50: 1568.7 | D50: ks | E50: 0.5 | F50: VIVAX
A51: 49 | B51: ACP-24CH70AERI+ | D51: ks | E51: 0.5 | F51: VIVAX
A52: 50 | D52: ks | E52: 0.5 | F52: VIVAX
A53: 51 | B53: M-DESIGN | D53: ks | E53: 0.5 | F53: VIVAX
A54: 52 | B54: ACP-09CH25AEMI+ R32 / I | C54: 599.86 | D54: ks | E54: 0.5 | F54: VIVAX
A55: 53 | B55: ACP-09CH25AEMI+ R32 / O | D55: ks | E55: 0.5 | F55: VIVAX
A56: 54 | B56: ACP-12CH35AEMI+ R32 / I | C56: 634.63 | D56: ks | E56: 0.5 | F56: VIVAX
A57: 55 | B57: ACP-12CH35AEMI+ R32 / O | D57: ks | E57: 0.5 | F57: VIVAX
A58: 56 | B58: ACP-18CH50AEMIs R32 / I | C58: 1002.54 | D58: ks | E58: 0.5 | F58: VIVAX
A59: 57 | B59: ACP-18CH50AEMIs R32 / O | D59: ks | E59: 0.5 | F59: VIVAX
A60: 58 | B60: ACP-24CH70AEMIs R32 / I | C60: 1348.86 | D60: ks | E60: 0.5 | F60: VIVAX
A61: 59 | B61: ACP-24CH70AEMIs R32 / O | D61: ks | E61: 0.5 | F61: VIVAX
A62: 60 | D62: ks | E62: 0.5 | F62: VIVAX
A63: 61 | B63: Q-DESIGN | D63: ks | E63: 0.5 | F63: VIVAX
A64: 62 | B64: ACP-09CH25AEQI+ R32 / I | C64: 577.46 | D64: ks | E64: 0.5 | F64: VIVAX
A65: 63 | B65: ACP-09CH25AEQI+ R32 / O | D65: ks | E65: 0.5 | F65: VIVAX
A66: 64 | B66: ACP-12CH35AEQI+ R32 / I | C66: 602.2 | D66: ks | E66: 0.5 | F66: VIVAX
A67: 65 | B67: ACP-12CH35AEQI+ R32 / O | D67: ks | E67: 0.5 | F67: VIVAX
A68: 66 | B68: ACP-18CH50AEQIs R32 / I | C68: 952.28 | D68: ks | E68: 0.5 | F68: VIVAX
A69: 67 | B69: ACP-18CH50AEQIs R32 / O | D69: ks | E69: 0.5 | F69: VIVAX
A70: 68 | B70: ACP-24CH70AEQIs R32 / I | C70: 1302.38 | D70: ks | E70: 0.5 | F70: VIVAX
A71: 69 | B71: ACP-24CH70AEQIs R32 / O | D71: ks | E71: 0.5 | F71: VIVAX
A72: 70 | D72: ks | E72: 0.5 | F72: VIVAX
A73: 71 | B73: Vnútorné nástenné jednotky R+ DESIG | D73: ks | E73: 0.5 | F73: VIVAX
A74: 72 | B74: ACP-09CH25AERI+/I WHITE | C74: 277.48 | D74: ks | E74: 0.5 | F74: VIVAX
A75: 73 | B75: ACP-09CH25AERI+/I GOLD | C75: 310.05 | D75: ks | E75: 0.5 | F75: VIVAX
A76: 74 | B76: ACP-09CH25AERI+/I SILVER | C76: 310.05 | D76: ks | E76: 0.5 | F76: VIVAX
A77: 75 | B77: ACP-12CH35AERI+/I WHITE | C77: 288.9 | D77: ks | E77: 0.5 | F77: VIVAX
A78: 76 | B78: ACP-12CH35AERI+/I GOLD | C78: 335.76 | D78: ks | E78: 0.5 | F78: VIVAX
A79: 77 | B79: ACP-12CH35AERI+/I SILVER | C79: 335.76 | D79: ks | E79: 0.5 | F79: VIVAX
A80: 78 | B80: ACP-12CH35AERI+/I MIRROR | C80: 335.76 | D80: ks | E80: 0.5 | F80: VIVAX
A81: 79 | B81: ACP-12CH35AERI+/I RED | C81: 335.76 | D81: ks | E81: 0.5 | F81: VIVAX
A82: 80 | B82: ACP-18CH50AERI+/I WHITE | C82: 408.28 | D82: ks | E82: 0.5 | F82: VIVAX
A83: 81 | B83: ACP-18CH50AERI+/I MIRROR | C83: 466.82 | D83: ks | E83: 0.5 | F83: VIVAX
A84: 82 | D84: ks | E84: 0.5 | F84: VIVAX
A85: 83 | B85: Vnútorné nástenné jednotky M-DESIG | D85: ks | E85: 0.5 | F85: VIVAX
A86: 84 | B86: ACP-07CH21AEMI/I | C86: 216.36 | D86: ks | E86: 0.5 | F86: VIVAX
A87: 85 | D87: ks | E87: 0.5 | F87: VIVAX
A88: 86 | B88: Vnútorné kazetové jednotky | D88: ks | E88: 0.5 | F88: VIVAX
A89: 87 | B89: ACP-09CC25AERI/I2 | C89: 547.56 | D89: ks | E89: 0.5 | F89: VIVAX
A90: 88 | B90: ACP-12CC35AERI/I3s | C90: 576.6 | D90: ks | E90: 0.5 | F90: VIVAX
A91: 89 | B91: ACP-18CC50AERI/I3s | C91: 628.25 | D91: ks | E91: 0.5 | F91: VIVAX
A92: 90 | D92: ks | E92: 0.5 | F92: VIVAX
A93: 91 | B93: Vnútorné parapetné jednotky | D93: ks | E93: 0.5 | F93: VIVAX
A94: 92 | B94: ACP-09CT25AERI/I3 | C94: 450.96 | D94: ks | E94: 0.5 | F94: VIVAX
A95: 93 | B95: ACP-12CT35AERI/I3 | C95: 484.82 | D95: ks | E95: 0.5 | F95: VIVAX
A96: 94 | B96: ACP-18CT50AERI/I3 | C96: 487.74 | D96: ks | E96: 0.5 | F96: VIVAX
A97: 95 | D97: ks | E97: 0.5 | F97: VIVAX
A98: 96 | B98: Vnútorné kanálové jednotky | D98: ks | E98: 0.5 | F98: VIVAX
A99: 97 | B99: ACP-12DT35AERI/I3s | C99: 637.08 | D99: ks | E99: 0.5 | F99: VIVAX
A100: 98 | B100: ACP-18DT50AERI/I3s | C100: 802.09 | D100: ks | E100: 0.5 | F100: VIVAX
...

Sheet Table_2
A1: Column1 | B1: Column2 | C1: Column3 | D1: Column4 | E1: Column5 | F1: Column6 | G1: Column7 | H1: Column8 | I1: Column9 | J1: Column10 | K1: Column11 | L1: Column12 | M1: Column13 | N1: Column14 | O1: Column15 | P1: Column16 | Q1: Column17 | R1: Column18 | S1: Column19 | T1: Column20 | U1: Column21 | V1: Column22 | W1: Column23 | X1: Column24 | Y1: Column25 | Z1: Column26 | AA1: Column27 | AB1: Column28 | AC1: Column29 | AD1: Column30 | AE1: Column31 | AF1: Column32 | AG1: Column33 | AH1: Column34 | AI1: Column35 | AJ1: Column36 | AK1: Column37 | AL1: Column38 | AM1: Column39 | AN1: Column40 | AO1: Column41 | AP1: Column42 | AQ1: Column43 | AR1: Column44 | AS1: Column45 | AT1: Column46 | AU1: Column47 | AV1: Column48 | AW1: Column49 | AX1: Column50 | AY1: Column51 | AZ1: Column52 | BA1: Column53 | BB1: Column54 | BC1: Column55 | BD1: Column56 | BE1: Column57 | BF1: Column58 | BG1: Column59 | BH1: Column60 | BI1: Column61 | BJ1: Column62 | BK1: Column63 | BL1: Column64 | BM1: Column65 | BN1: Column66 | BO1: Column67 | BP1: Column68 | BQ1: Column69 | BR1: Column70 | BS1: Column71 | BT1: Column72 | BU1: Column73 | BV1: Column74 | BW1: Column75 | BX1: Column76 | BY1: Column77 | BZ1: Column78 | CA1: Column79 | CB1: Column80 | CC1: Column81 | CD1: Column82 | CE1: Column83 | CF1: Column84 | CG1: Column85 | CH1: Column86 | CI1: Column87 | CJ1: Column88 | CK1: Column89 | CL1: Column90 | CM1: Column91 | CN1: Column92 | CO1: Column93 | CP1: Column94 | CQ1: Column95 | CR1: Column96 | CS1: Column97 | CT1: Column98 | CU1: Column99 | CV1: Column100 | CW1: Column101 | CX1: Column102 | CY1: Column103 | CZ1: Column104 | DA1: Column105 | DB1: Column106 | DC1: Column107 | DD1: Column108 | DE1: Column109 | DF1: Column110 | DG1: Column111 | DH1: Column112 | DI1: Column113 | DJ1: Column114 | DK1: Column115 | DL1: Column116 | DM1: Column117 | DN1: Column118 | DO1: Column119 | DP1: Column120
A3: Cenník montážneho materiálu Platný od 1.4.2024
V4: Skl.číslo | AB4: Sklad | AH4: Popis | BS4: M.j. | BU4: Nákupná cena v EUR bez DPH
AH5: Predizolované medené potrubie
A6: 2000 | AB6: s | AH6: Cu potrubie predizolované 6 (1/4" x 0,8) 50m | BS6: m | BU6: 1.91
A7: 2002 | AB7: s | AH7: Cu potrubie predizolované 10 (3/8" x 0,8) 50m | BS7: m | BU7: 2.54
A8: 2004 | AB8: s | AH8: Cu potrubie predizolované 12 (1/2" x 0,8) 50m | BS8: m | BU8: 4.15
A9: 2001 | AB9: o | AH9: Cu potrubie predizolované 6 (1/4" x 1) 50m | BS9: m | BU9: 2.29
A10: 2003 | AB10: o | AH10: Cu potrubie predizolované 10 (3/8" x 1) 50m | BS10: m | BU10: 3.25
A11: 2005 | AB11: o | AH11: Cu potrubie predizolované 12 (1/2" x 1) 50m | BS11: m | BU11: 5.89
A12: 2006 | AB12: s | AH12: Cu potrubie predizolované 16 (5/8" x 1,0)50m | BS12: m | BU12: 6.35
A13: 2007 | AB13: s | AH13: Cu potrubie predizolované 18 (3/4" x 1,0) 25m | BS13: m | BU13: 8.38
A14: 2008 | AB14: s | AH14: Cu potrubie predizolované 22 (7/8" x 1,0) 25m | BS14: m | BU14: 9.21
AH15: Predizolovaná dvojica medeného potrubia (DUAL)
A16: 2010 | AB16: s | AH16: Cu potrubie predizolované DUO 6+10 (1/4"+3/8"x0,8) 25m | BS16: m | BU16: 4.2
A17: 2011 | AB17: s | AH17: Cu potrubie predizolované DUO 6+12 (1/4"+1/2"x0,8) 25m | BS17: m | BU17: 5.36
A18: 2012 | AB18: s | AH18: Cu potrubie predizolované DUO 10-16 (3/8"x5/8") 25m | BS18: m | BU18: 8.95
A19: 2013 | AB19: o | AH19: Cu potrubie predizolované DUO 6+10 (1/4"+3/8"x1) 25m | BS19: m | BU19: 6.39
A20: 2014 | AB20: o | AH20: Cu potrubie predizolované DUO 6+12 (1/4"+1/2"x1) 25m | BS20: m | BU20: 7.34
AH21: Predizolovaná dvojica medeného potrubia (DUAL - UV Resistant)
A22: 201430 | AB22: s | AH22: Cu potrubie predizolované DUO 6+10 (1/4"+3/8"x0,8) 25m | BS22: m | BU22: 4.44
A23: 201431 | AB23: s | AH23: Cu potrubie predizolované DUO 6+12 (1/4"+1/2"x0,8) 25m | BS23: m | BU23: 5.49
AH24: Izolačné pásky
A25: 2015 | AB25: s | AH25: Samolepiaca izolačná páska - čierna | BS25: ks | BU25: 7.8
A26: 2016 | AB26: s | AH26: Samolepiaca izolačná páska -biela | BS26: ks | BU26: 13.4
A27: 2017 | AB27: s | AH27: Al páska, hliníková 50mm x 50m | BS27: ks | BU27: 5.7
A28: 2018 | AB28: s | AH28: Al páska, hliníková 75mm x 50m | BS28: ks | BU28: 8.8
AH29: Čistiace a dezinfekčné prostriedky
A30: 5001 | AB30: s | AH30: RTU Evaporator 1l , čistiaci a dezinfekčný roztok výparníka | BS30: ks | BU30: 21.8
A31: 5002 | AB31: s | AH31: RTU Evaporator 5l , čistiaci a dezinfekčný roztok výparníka | BS31: ks | BU31: 24.6
A32: 5004 | AB32: s | AH32: CondenCide 5l, koncentrát - čistič výparníka s dezinfekcia | BS32: ks | BU32: 42.2
A33: 5017 | AB33: s | AH33: SuperClean 5l, koncentrát pre veľmi znečistené kondenzátory | BS33: ks | BU33: 86.9
A34: 5008 | AB34: s | AH34: Easy Care sprej-čistič a desinfekcia výparníka | BS34: ks | BU34: 14.1
A35: 5015 | AB35: s | AH35: Ulith - detekčná pena - sprej | BS35: ks | BU35: 2.8
A36: 5016 | AB36: o | AH36: Rothenberger - Sanifresh - čistič a dezinfekcia | BS36: ks | BU36: 15.9
AH37: Konzoly
A38: 6011 | AB38: s | AH38: Konzola biela - 465 | BS38: set | BU38: 18
A39: 6002 | AB39: s | AH39: Konzola biela - 550 | BS39: set | BU39: 20
A40: 6003 | AB40: s | AH40: Konzola biela - 620 | BS40: set | BU40: 28
A41: 6004 | AB41: s | AH41: Konzola biela - 700 | BS41: set | BU41: 44
A42: 6005 | AB42: s | AH42: Nastaviteľná konzola - 420 | BS42: set | BU42: 21
A43: 6006 | AB43: s | AH43: Nastaviteľná konzola - 550 | BS43: set | BU43: 24
A44: 6020 | AB44: s | AH44: Strešna konzola | BS44: set | BU44: 45
A45: 6008 | AB45: o | AH45: Konzola pre TČ - SP700 - 25 cm | BS45: set | BU45: 31
A46: 6009 | AB46: o | AH46: Konzola pre TČ - SP740 - 40 cm | BS46: set | BU46: 32
A47: 6016 | AB47: o | AH47: Konzola pre TČ - Frame Foot | BS47: set | BU47: 108
A48: Nosnosť konzol: 420 - 120 kg, 550 - 140 kg, 620 - 160 kg, 700 - 170 kg Silentbloky
A49: 6021 | AB49: s | AH49: Silentblok - konus - sada 4 ks | BS49: bal. | BU49: 3.32
A50: 6023 | AB50: s | AH50: Antivibrační silentbloky - žltá sada 4 ks do 200 kg | BS50: sada | BU50: 16.8
A51: 6023 | AB51: s | AH51: Antivibrační silentbloky - zelená sada 4 ks do 100 kg | BS51: sada | BU51: 16.8
A52: 6024 | AB52: s | AH52: Gumové Nôžky 40 mm - sada 4 ks | BS52: sada | BU52: 6.1
AH53: Montážne bloky pod klimatizácie
A54: 6055 | AB54: s | AH54: Montážny blok 450 - biely, nosnosť 200kg | BS54: ks | BU54: 3.1
A55: 6056 | AB55: s | AH55: Montážny blok 1000 - biely, nosnosť 200kg | BS55: ks | BU55: 6.3
A56: 6061 | AB56: s | AH56: Koncový kryt montážneho bloku biely | BS56: ks | BU56: 0.6
A57: 6065 | AB57: s | AH57: Podkladový blok 400 - gumený | BS57: ks | BU57: 13.2
A58: 6066 | AB58: s | AH58: Podkladový blok 600 - gumený | BS58: ks | BU58: 17.9
A59: 6067 | AB59: s | AH59: Podkladový blok 1000 - gumený | BS59: ks | BU59: 30.3
A62: Čerpadlá
A63: 7000 | J63: s | N63: SI 27 Sauermann 10 l/h , max. 6m | AX63: ks | BC63: 51
A64: 7010 | J64: s | N64: Delta Pack - rohové čerpadlo s lištou 8 l/h , max. 6m | AX64: ks | BC64: 96
A65: 7012 | J65: s | N65: SI 83 čerpadlo se zásobníkem 2l , 500l/h , max.4,2m | AX65: ks | BC65: 79
A66: 7014 | J66: s | N66: MiniBlue - čerpadlo + teplotní čidla | AX66: ks | BC66: 102
A67: 7028 | J67: s | N67: Micro Blue - so zásobníkom a akustickým alarmom | AX67: ks | BC67: 101
A68: 7035 | J68: s | N68: COMBI-Refco čerpadlo, 42l, sacia výška 3m, výtlak 20m | AX68: ks | BC68: 91
A69: 7036 | J69: s | N69: GOBI II-Refco čerpadlo pod klimatizáciu | AX69: ks | BC69: 108
A70: Príslušenstvo na odvod kondenzátu
A71: 7015 | J71: s | N71: PVC hadička zosilnená k čerpadlám 6x9 mm , 50m | AX71: ks | BC71: 15.8
A72: 7100 | J72: s | N72: Hadička odvodu kondenzátu 16 mm , vo vnútri hladká 30m | AX72: ks | BC72: 23.4
A73: 7101 | J73: s | N73: Y spojka odvodu kondenzátu | AX73: ks | BC73: 0.9
A74: 7102 | J74: s | N74: Sifon odvodu kondenzátu - univerzálny | AX74: ks | BC74: 7.2
A75: 7103 | J75: s | N75: Sifon podomietkový s guličkou DN 32/20 | AX75: ks | BC75: 31.1
A76: 7110 | J76: s | N76: Redukcia Yellow 16/20 - 18 - 16 | AX76: ks | BC76: 1.65
A77: 7111 | J77: s | N77: Redukcia Red 18/20 - 18 - 16 | AX77: ks | BC77: 1.65
A78: 7112 | J78: s | N78: Redukcia Blue 20/20 - 18 - 16 | AX78: ks | BC78: 1.65
A79: 7113 | J79: s | N79: Redukcia Green 25/20 - 18 - 16 | AX79: ks | BC79: 1.86
A80: 7114 | J80: s | N80: Redukcia Grey 32/20 - 18 - 16 | AX80: ks | BC80: 1.86
A81: 7150 | J81: o | N81: PVC potrubie kondenzátu 20mm | AX81: m | BC81: 0.77
A82: 7151 | J82: o | N82: Koleno 90° 20mm | AX82: ks | BC82: 1.52
... A94: 7166 | J94: o | N94: Príchytka potrubia 25mm | AX94: ks | BC94: 0.3
A95: Plastové lišty ECO
A96: 8000 | J96: s | N96: Lišta 80 mm , dĺžka 2m | AX96: m | BC96: 6.36
A97: 8001 | J97: s | N97: Roh vnútorný 80 mm | AX97: ks | BC97: 1.94
A98: 8002 | J98: s | N98: Roh vonkajší 80 mm | AX98: ks | BC98: 1.94
A99: 8003 | J99: s | N99: Roh plochý 80 mm | AX99: ks | BC99: 1.94
A100: 8004 | J100: s | N100: T - kus 80 mm | AX100: ks | BC100: 1.94
A101: 8005 | J101: s | N101: Spojka 80 mm | AX101: ks | BC101: 0.99
A102: 8006 | J102: s | N102: Koncový kryt 80 mm | AX102: ks | BC102: 1.94
A103: 8007 | J103: s | N103: Koncový stenový kryt 80 mm | AX103: ks | BC103: 1.94
A104: 8009 | J104: s | N104: Rozeta lišty 80 mm | AX104: ks | BC104: 2.19
A105: Na objednávku vieme zabezpečiť lišty a tvarovky ECO so šírkou 105mm
A106: Plastové lišty OPTIMAL
A107: 8020 | J107: s | N107: Lišta Optimal 80 mm ,dĺžka 2 metre | AX107: m | BC107: 3.3
A108: 8021 | J108: s | N108: Roh vnútorný Optimal 80 mm | AX108: ks | BC108: 1.37
A109: 8022 | J109: s | N109: Roh vonkajší Optimal 80 mm | AX109: ks | BC109: 1.37
A110: 8023 | J110: s | N110: Roh plochý Optimal 80 mm | AX110: ks | BC110: 1.79
A111: 8024 | J111: s | N111: T- kus Optimal 80 mm | AX111: ks | BC111: 3.29
A112: 8025 | J112: s | N112: Spojka Optimal 80 mm | AX112: ks | BC112: 0.81
A113: 8026 | J113: s | N113: Koncový kryt Optimal 80 mm | AX113: ks | BC113: 1.29
A114: 8027 | J114: s | N114: Koncový kryt stenový Optimal 80 mm | AX114: ks | BC114: 2.01
...

Sheet Hárok2
A1: Dátum | B1: Meno Zákazníka | C1: Telefónne číslo | D1: Platba | E1: Druh Zásahu | F1: Platba_partner | G1: Suma | H1: PODIEL KLIMAZONE | I1: PODIEL KLIMAFRESH | J1: KOMENTY | K1: Iné info | L1: Adresa | M1: Mesiac | N1: Kategória
A2: 45298 | B2: De Paul Miko | C2: 421903250175 | D2: faktura | E2: Montaz | F2: faktura | G2: 280 | I2: 200 | J2: zistit | L2: Muskatova 20, Jur | M2: 2024-01 | N2: Iné
A3: 45298 | B3: Rudolf Herenyi | D3: neznáme | E3: Servis 2+1 | F3: faktura | I3: 74 | J3: pan chce chladivo doplnit do 4 jednotiek minimalne do 2x - cena za plnenie je 100eur na jednotku | L3: neznáme | M3: 2024-01 | N3: Servis
A4: 45298 | B4: Marek Bican | D4: neznáme | E4: Servis 2+1 | F4: hotovost | G4: 150 | I4: 74 | L4: neznáme | M4: 2024-01 | N4: Servis
A5: 45298 | B5: Jozef Stuska | C5: 421915158267 | D5: neznáme | E5: nic | F5: nic | I5: 30 | L5: neznáme | M5: 2024-01 | N5: Iné
A6: 45298 | B6: Stubna S | C6: 421918737666 | D6: neznáme | E6: Servis 2+1 | F6: hotovost | G6: 160 | H6: 80 | I6: 74 | L6: neznáme | M6: 2024-01 | N6: Servis
A7: 45298 | B7: Svetlana Durisova | C7: 421905745264 | D7: neznáme | E7: Servis 4+1 | F7: fa | I7: 140 | L7: neznáme | M7: 2024-01 | N7: Servis
A8: 45298 | B8: Lavicanova | C8: ++421911105075 , ++421904252612 | D8: neznáme | E8: Servis 2+1 | F8: hotovost | G8: 150 | H8: 76 | I8: 74 | L8: neznáme | M8: 2024-01 | N8: Servis
A9: 45298 | B9: Pavla Krauspe | C9: 421948461110 | D9: neznáme | E9: Servis 1+1 | F9: hotovost | G9: 80 | I9: 40 | L9: neznáme | M9: 2024-01 | N9: Servis
A10: 45329 | B10: Petra Adams | C10: 421902705618 | D10: neznáme | E10: Servis 2+1 | F10: hotovost | G10: 170 | H10: 90 | I10: 74 | L10: neznáme | M10: 2024-02 | N10: Servis
A11: 45329 | B11: Viera Fudincova | C11: 421904906349 | D11: neznáme | E11: Servis 2+1 | F11: FA | I11: 74 | L11: neznáme | M11: 2024-02 | N11: Servis
A12: 45329 | B12: Farkasova andrea | C12: 421918520144 | D12: neznáme | E12: Servis 1+1 | F12: hotovost | G12: 90 | H12: 50 | I12: 40 | J12: objednat cerpadlo a vymenit ho cena 200 eur | L12: neznáme | M12: 2024-02 | N12: Servis
A13: 45329 | B13: Petra Puhovychova | C13: 421902705618 | D13: neznáme | E13: Servis 1+1 | F13: hotovost | G13: 80 | H13: 40 | I13: 40 | L13: neznáme | M13: 2024-02 | N13: Servis
A14: 45329 | B14: Barbora Kominova | D14: neznáme | E14: Servis 1+1 | F14: Fa | I14: 40 | L14: neznáme | M14: 2024-02 | N14: Servis
A15: 45329 | B15: Pavel Bjadinsky | C15: 421917449308 | D15: neznáme | E15: Servis 1+1 | F15: hotovost | G15: 120 | H15: 50 | I15: 70 | L15: neznáme | M15: 2024-02 | N15: Servis
A16: 45329 | B16: Monika Le | C16: 421948321700 | D16: neznáme | E16: Servis 1+1 | F16: hotovost | G16: 80 | H16: 40 | I16: 40 | L16: neznáme | M16: 2024-02 | N16: Servis
A17: 45357 | B17: Zuzana Litvova | D17: neznáme | E17: Serivs 1+1 | F17: hotovost | G17: 80 | H17: 40 | I17: 40 | J17: Cistenie a mozno doplnit navyse? | L17: neznáme | M17: 2024-03 | N17: Iné
A18: 45357 | B18: Olga Znachorova | D18: neznáme | E18: Serivs 1+1 | F18: hotovost | G18: 80 | H18: 40 | I18: 40 | L18: neznáme | M18: 2024-03 | N18: Iné
A19: 45357 | B19: Lubica Bednarova | D19: neznáme | E19: Servis 2+1 | F19: hotovost | G19: 180 | H19: 90 | I19: 90 | L19: neznáme | M19: 2024-03 | N19: Servis
A20: 45357 | B20: Marek Palkech | C20: 421905449107 | D20: neznáme | E20: Serivs 1+1 | F20: hotovost | G20: 80 | H20: 40 | I20: 40 | L20: neznáme | M20: 2024-03 | N20: Iné
A21: 45358 | B21: Pokrivcakova Petra | D21: neznáme | E21: Servis 1+1 | F21: hotovost | G21: 80 | H21: 40 | I21: 40 | L21: neznáme | M21: 2024-03 | N21: Servis
A22: 45358 | B22: Maria Fecerova | D22: neznáme | E22: Servis 2+1 | F22: NEDVIHALA | G22: 0 | H22: 0 | I22: 0 | L22: neznáme | M22: 2024-03 | N22: Servis
A23: 45358 | B23: Kandlova Katarina | D23: neznáme | E23: Doplnit chladivo | F23: hotovost | G23: 200 | H23: 80 | I23: 120 | L23: neznáme | M23: 2024-03 | N23: Iné
A24: 45358 | B24: Dusan Vavro | D24: neznáme | E24: Servis 4+1 | F24: hotovost | G24: 280 | H24: 140 | I24: 140 | L24: neznáme | M24: 2024-03 | N24: Servis
A25: 45358 | B25: Durovcik D | C25: 421902430354 | D25: neznáme | E25: Servis 2+1 + diagnostika | F25: hotovost | G25: 200 | H25: 100 | I25: 100 | J25: objednat 6 ovladacov od klimatizacie RC08A Airwell ovladac, a 2x ovladac od vnutornej jednotky AWSI-HND018-N11 | L25: neznáme | M25: 2024-03 | N25: Servis
A26: 45358 | B26: Miro Bilik | C26: 421907470050 | D26: neznáme | E26: Servis 1+1 | F26: hotovost | G26: 80 | H26: 40 | I26: 40 | L26: neznáme | M26: 2024-03 | N26: Servis
A27: 45388 | B27: Juraj Chandoga | C27: 421918497788 | D27: neznáme | E27: Serivs 1+1 | F27: faktura | H27: 40 | I27: 40 | L27: neznáme | M27: 2024-04 | N27: Iné
A28: 45388 | B28: Juraj Fruhwald | C28: 918333096 | D28: neznáme | E28: Servis 2+1 | F28: hotovost | G28: 150 | H28: 75 | I28: 75 | L28: neznáme | M28: 2024-04 | N28: Servis
A29: 45389 | B29: Jager Jozef | C29: 421915574846 | D29: neznáme | E29: Servis 1+1 | F29: hotovost | G29: 100 | H29: 45 | I29: 55 | J29: vyjazd 75km, nacenit mu novu 1+1 klimu 3.5 kw a dohodnut montaz | L29: neznáme | M29: 2024-04 | N29: Servis
A30: 45389 | B30: Sobolik S | C30: 421902705618 | D30: hotovost | E30: Servis 1+1 | F30: hotovost | G30: 80 | H30: 40 | I30: 40 | L30: Tomasikova 50/A | M30: 2024-04 | N30: Servis
A31: 45389 | B31: Red Lion Bar | C31: 421915574846 | D31: neznáme | E31: Servis 1+1 | F31: FA | L31: neznáme | M31: 2024-04 | N31: Servis
A32: 45389 | B32: Potocky P | C32: 421915196062 | D32: hotovost | E32: Servis 3+1 | F32: FA | I32: 105 | L32: Mierova 27 | M32: 2024-04 | N32: Servis
A33: 45389 | B33: Katarina Sarkozi | C33: 421905206614 | D33: hotovost | E33: Servis 3+1 | F33: hotovost | G33: 240 | H33: 135 | I33: 105 | L33: Haburska 18, Ruzinov | M33: 2024-04 | N33: Servis
A34: 45389 | B34: Martin Pavelek | C34: 421902705618 | D34: neznáme | E34: Servis 1+1 | F34: hotovost | G34: 60 | H34: 20 | I34: 40 | L34: neznáme | M34: 2024-04 | N34: Servis
A35: 45411 | B35: Montaz | D35: neznáme | E35: neznáme | L35: neznáme | M35: 2024-04 | N35: Iné
A36: 45411 | B36: Monika | C36: ++421903469884 , ++421902705618 , ++421944169071 , ++421901737787 | D36: neznáme | E36: neznáme | L36: neznáme | M36: 2024-04 | N36: Iné
A37: 45411 | B37: Mmgbenzo | C37: 421904087288 | D37: neznáme | E37: neznáme | L37: neznáme | M37: 2024-04 | N37: Iné
A38: 45411 | B38: Miriam | C38: 421902705618 | D38: neznáme | E38: neznáme | L38: neznáme | M38: 2024-04 | N38: Iné
A39: 45411 | B39: Ivan | C39: ++421915574846 , ++421902705618 | D39: neznáme | E39: neznáme | L39: neznáme | M39: 2024-04 | N39: Iné
A40: 45411 | B40: Miro | C40: 421905472808 | D40: neznáme | E40: neznáme | L40: neznáme | M40: 2024-04 | N40: Iné
A41: 45411 | B41: Ivana | C41: 421902705618 | D41: neznáme | E41: neznáme | L41: neznáme | M41: 2024-04 | N41: Iné
A42: 45411 | B42: Husarovaservis | C42: 421908911322 | D42: neznáme | E42: neznáme | L42: neznáme | M42: 2024-04 | N42: Iné
A43: 45411 | B43: Jan | C43: ++421948828105 , ++421903826027 | D43: neznáme | E43: neznáme | L43: Krasnohorska 22 | M43: 2024-04 | N43: Iné
A44: 45411 | B44: Jakub | C44: 421908951010 | D44: neznáme | E44: neznáme | L44: Konvalinkova 2 | M44: 2024-04 | N44: Iné
A45: 45411 | B45: Jagerjager | C45: 421902705618 | D45: neznáme | E45: neznáme | L45: neznáme | M45: 2024-04 | N45: Iné
A46: 45411 | B46: Jager | C46: 421905854198 | D46: neznáme | E46: neznáme | L46: neznáme | M46: 2024-04 | N46: Iné
A47: 45411 | B47: Inna | C47: 421902705618 | D47: neznáme | E47: neznáme | L47: neznáme | M47: 2024-04 | N47: Iné
A48: 45411 | B48: J | C48: 421918712719 | D48: neznáme | E48: neznáme | L48: neznáme | M48: 2024-04 | N48: Iné
A49: 45411 | B49: Mmgbarber | C49: 421904087288 | D49: neznáme | E49: neznáme | L49: neznáme | M49: 2024-04 | N49: Iné
A50: 45411 | B50: Sona | C50: 421902705618 | D50: neznáme | E50: neznáme | L50: neznáme | M50: 2024-04 | N50: Iné
A51: 45411 | B51: H | C51: 421919264307 | D51: neznáme | E51: neznáme | L51: neznáme | M51: 2024-04 | N51: Iné
A52: 45411 | B52: Durovcik | C52: 421903438235 | D52: neznáme | E52: neznáme | L52: neznáme | M52: 2024-04 | N52: Iné
A53: 45411 | B53: Dusan | C53: 421910220772 | D53: neznáme | E53: neznáme | L53: neznáme | M53: 2024-04 | N53: Iné
A54: 45411 | B54: Dusanvavro | C54: 421911980082 | D54: neznáme | E54: neznáme | L54: neznáme | M54: 2024-04 | N54: Iné
A55: 45411 | B55: Zuzana | C55: ++421902705618 , ++421908515148 , ++421903572188 , ++421907717397 | D55: hotovost | E55: neznáme | L55: Grosslingova 47, BA | M55: 2024-04 | N55: Iné
A56: 45411 | B56: Zelinka | C56: 421903757149 | D56: neznáme | E56: 1+1 servis | F56: neznáme | G56: 80 | H56: 40 | I56: 40 | L56: Stavbarska 36 | M56: 2024-04 | N56: Iné
A57: 45411 | B57: E | C57: 421911964313 | D57: neznáme | E57: neznáme | L57: neznáme | M57: 2024-04 | N57: Iné
A58: 45411 | B58: Eduard | C58: 421903969377 | D58: neznáme | E58: neznáme | L58: Juraja fandlyho 36 | M58: 2024-04 | N58: Iné
A59: 45411 | B59: Eliska | C59: 421902705618 | D59: neznáme | E59: neznáme | L59: neznáme | M59: 2024-04 | N59: Iné
A60: 45411 | B60: Kunakova | C60: 421948192444 | D60: neznáme | E60: Servis 3+1 | F60: FA | I60: 105 | L60: neznáme | M60: 2024-04 | N60: Servis
A61: 45411 | B61: P | C61: ++421949104885 , ++421903321928 , ++421902349977 , ++421905586995 , ++421911391747 , ++421911201535 , ++421910810253 , ++421918637556 , ++421902180795 , ++421903777307 , ++421944154176 , ++421908722933 , ++421905319932 , ++421903763042 , ++421905462027 | D61: hotovost | E61: neznáme | L61: Valivova 14 | M61: 2024-04 | N61: Iné
A62: 45411 | B62: Olsak | C62: 421940597154 | D62: neznáme | E62: neznáme | L62: neznáme | M62: 2024-04 | N62: Iné
A63: 45411 | B63: Farkasova | C63: 421905470334 | D63: neznáme | E63: neznáme | L63: neznáme | M63: 2024-04 | N63: Iné
A64: 45411 | B64: Hedvig | C64: 421902705618 | D64: neznáme | E64: neznáme | L64: neznáme | M64: 2024-04 | N64: Iné
A65: 45411 | B65: Filip | C65: 421902705618 | D65: hotovost | E65: neznáme | L65: Povazska 5 | M65: 2024-04 | N65: Iné
A66: 45411 | B66: Zajacovadiagnostika | D66: neznáme | E66: neznáme | L66: neznáme | M66: 2024-04 | N66: Iné
A67: 45411 | B67: Olibik | C67: 421944418404 | D67: neznáme | E67: neznáme | L67: neznáme | M67: 2024-04 | N67: Iné
A68: 45411 | B68: Obhliadka | D68: neznáme | E68: neznáme | L68: neznáme | M68: 2024-04 | N68: Iné
A69: 45411 | B69: Galova | C69: 421903736305 | D69: neznáme | E69: neznáme | L69: neznáme | M69: 2024-04 | N69: Iné
A70: 45411 | B70: Nikoleta | C70: 421948766172 | D70: neznáme | E70: neznáme | L70: neznáme | M70: 2024-04 | N70: Iné
A71: 45411 | B71: Nikola | C71: 421902705618 | D71: neznáme | E71: neznáme | L71: neznáme | M71: 2024-04 | N71: Iné
A72: 45411 | B72: Girgel | C72: 421908139562 | D72: neznáme | E72: neznáme | L72: neznáme | M72: 2024-04 | N72: Iné
A73: 45411 | B73: Nikol | C73: 421948423939 | D73: neznáme | E73: neznáme | L73: Konopna 13 | M73: 2024-04 | N73: Iné
A74: 45411 | B74: Glaserova | C74: 421944436585 | D74: neznáme | E74: neznáme | L74: neznáme | M74: 2024-04 | N74: Iné
A75: 45411 | B75: Nasklient | C75: ++421903722288 , ++421910620248 | D75: neznáme | E75: neznáme | L75: neznáme | M75: 2024-04 | N75: Iné
A76: 45411 | B76: N | D76: neznáme | E76: neznáme | L76: neznáme | M76: 2024-04 | N76: Iné
A77: 45411 | B77: Muchvova | C77: 421904744818 | D77: neznáme | E77: neznáme | L77: neznáme | M77: 2024-04 | N77: Iné
A78: 45411 | B78: Findurova | C78: 421904253717 | D78: FA | E78: 2x hĺbkové čistenie | F78: FA | J78: vyčiestené, pravdepodobne bude iný problém, reklamacia servisu | L78: Námestie hraničiarov | M78: 2024-04 | N78: Iné
A79: 45411 | B79: Milko | C79: 421902705618 | D79: neznáme | E79: neznáme | L79: neznáme | M79: 2024-04 | N79: Iné
A80: 45411 | B80: Matej | C80: ++421918235545 , ++421911255730 | D80: neznáme | E80: neznáme | L80: neznáme | M80: 2024-04 | N80: Iné
A81: 45411 | B81: Jana | C81: ++421902705618 , ++421905684306 | D81: hotovost | E81: neznáme | L81: Vlastenecke namestie 7 | M81: 2024-04 | N81: Iné
A82: 45411 | B82: Klima | C82: 421910878413 | D82: neznáme | E82: neznáme | L82: neznáme | M82: 2024-04 | N82: Iné
A83: 45411 | B83: Klimafresh | C83: 421948192444 | D83: neznáme | E83: neznáme | L83: neznáme | M83: 2024-04 | N83: Iné
A84: 45411 | B84: Kmec | C84: 421948377122 | D84: neznáme | E84: neznáme | L84: neznáme | M84: 2024-04 | N84: Iné
A85: 45411 | B85: M | C85: ++421915574846 , ++421903425584 , ++421911606156 , ++421944937552 , ++421903402814 , ++421911773957 | D85: neznáme | E85: neznáme | L85: neznáme | M85: 2024-04 | N85: Iné
A86: 45411 | B86: Kmecik | C86: 421944154176 | D86: neznáme | E86: neznáme | L86: Plynárenská 3a, 821 09 Bratislava-Ružinov, Slovensko | M86: 2024-04 | N86: Iné
A87: 45411 | B87: Lukas | C87: 421902705618 | D87: hotovost | E87: neznáme | L87: Medvedovej 20 | M87: 2024-04 | N87: Iné
A88: 45411 | B88: Usmevakodar | C88: 421918022534 | D88: neznáme | E88: neznáme | L88: neznáme | M88: 2024-04 | N88: Iné
A89: 45411 | B89: Viktor | C89: 421907462282 | D89: neznáme | E89: neznáme | L89: neznáme | M89: 2024-04 | N89: Iné
A90: 45411 | B90: Kollaty | C90: 421911934657 | D90: neznáme | E90: neznáme | L90: neznáme | M90: 2024-04 | N90: Iné
A91: 45411 | B91: Lubica | C91: ++421905828569 , ++421902705618 | D91: neznáme | E91: neznáme | L91: neznáme | M91: 2024-04 | N91: Iné
A92: 45411 | B92: V | D92: neznáme | E92: neznáme | L92: neznáme | M92: 2024-04 | N92: Iné
A93: 45411 | B93: Lenka | C93: 421902353161 | D93: FA | E93: neznáme | L93: Vychovskehko 5 | M93: 2024-04 | N93: Iné
A94: 45411 | B94: Kosicky | C94: 421903856511 | D94: hotovost | E94: neznáme | L94: Rekreacny rad | M94: 2024-04 | N94: Iné
A95: 45411 | B95: Lavicanova | C95: 421908846543 | D95: neznáme | E95: neznáme | L95: neznáme | M95: 2024-04 | N95: Iné
A96: 45411 | B96: Lauda | C96: 421904325329 | D96: neznáme | E96: neznáme | L96: neznáme | M96: 2024-04 | N96: Iné
A97: 45411 | B97: Kretter | C97: =42190 +4212849 -> 4255039 | D97: neznáme | E97: neznáme | L97: neznáme | M97: 2024-04 | N97: Iné
A98: 45411 | B98: Kristina | C98: ++421902705618 , ++421915730855 | D98: neznáme | E98: neznáme | L98: Sona Sadtnera 39 | M98: 2024-04 | N98: Iné
A99: 45411 | B99: L | C99: ++421949590014 , ++421907701068 | D99: neznáme | E99: neznáme | L99: neznáme | M99: 2024-04 | N99: Iné
A100: 45411 | B100: Vaskova | C100: 421903885703 | D100: neznáme | E100: neznáme | L100: neznáme | M100: 2024-04 | N100: Iné
...

Sheet GPT cache
KEC659974: {"hash":"6d0a1205c28edd90b9716d01def9fb6b6ba74665b1ba1fc770ee03106666d940","version":1,"value":"[[\"The formula =RC[-2]*(1-RC[-1]) in Microsoft Excel is written using R1C1 reference style. It calculates the value by performing the following steps:\\n\\n1. **RC[-2]**: This part of the formula refers to a cell that is two columns to the left of the current cell in the same row. For example, if the formula is in cell C5, RC[-2] refers to cell A5.\\n\\n2. **RC[-1]**: This refers to the cell immediately to the left of the current cell in the same row. If the formula is in cell C5, RC[-1] refers to cell B5.\\n\\n3. **1-RC[-1]**: This expression subtracts the value in the cell referred to by RC[-1] from 1.\\n\\n4. **RC[-2]*(1-RC[-1])**: Finally, the formula multiplies the value from step 1 (RC[-2]) by the result from step 3 (1-RC[-1]). This results in a new value that is derived by reducing the value in RC[-2] by a percentage equal to the value in RC[-1].\\n\\nIn summary, this formula reduces the value in a cell two columns to the left by a percentage specified in the cell immediately to the left, and outputs the result in the cell where the formula is placed.\"]]"}
